[
  {
    "date": "2021-03-31",
    "pre_value": 10000000.0,
    "post_value": 10000000.0,
    "cost": 0.0,
    "turnover": 0.628218,
    "old_weights": {},
    "new_weights": {
      "META": 0.026379,
      "GOOGL": 0.038322,
      "GOOG": 0.043821,
      "INTC": 0.046117,
      "JPM": 0.054051,
      "PLTR": 0.0102,
      "BAC": 0.066535,
      "XOM": 0.070681,
      "MU": 0.01083,
      "T": 0.039807,
      "AAL": 0.088794,
      "WFC": 0.00835,
      "CVX": 0.017745,
      "CSCO": 0.097475,
      "DKNG": 0.009111
    }
  },
  {
    "date": "2021-04-30",
    "pre_value": 10103182.24,
    "post_value": 10103182.24,
    "cost": 0.0,
    "turnover": 0.986311,
    "old_weights": {
      "TSLA": 0.0,
      "AAPL": 0.0,
      "AMZN": 0.0,
      "NIO": 0.0,
      "BABA": 0.0,
      "MSFT": 0.0,
      "META": 0.026379,
      "NVDA": 0.0,
      "AMD": 0.0,
      "ZM": 0.0,
      "GOOGL": 0.038322,
      "GOOG": 0.043821,
      "NFLX": 0.0,
      "CRM": 0.0,
      "INTC": 0.046117,
      "XYZ": 0.0,
      "PYPL": 0.0,
      "DIS": 0.0,
      "JPM": 0.054051,
      "PLUG": 0.0,
      "PFE": 0.0,
      "PLTR": 0.0102,
      "BAC": 0.066535,
      "SHOP": 0.0,
      "SNOW": 0.0,
      "C": 0.0,
      "XOM": 0.070681,
      "MU": 0.01083,
      "T": 0.039807,
      "AAL": 0.088794,
      "QCOM": 0.0,
      "UBER": 0.0,
      "TSM": 0.0,
      "JD": 0.0,
      "WFC": 0.00835,
      "WMT": 0.0,
      "SNAP": 0.0,
      "VZ": 0.0,
      "QS": 0.0,
      "CCL": 0.0,
      "CVX": 0.017745,
      "CSCO": 0.097475,
      "KO": 0.0,
      "CMCSA": 0.0,
      "PINS": 0.0,
      "DKNG": 0.009111,
      "DOCU": 0.0,
      "UAL": 0.0,
      "NKE": 0.0,
      "MS": 0.0
    },
    "new_weights": {
      "MSFT": 0.010196,
      "META": 0.093683,
      "GOOGL": 0.067579,
      "GOOG": 0.1,
      "XYZ": 0.005478,
      "JPM": 0.005686,
      "PFE": 0.080768,
      "BAC": 0.1,
      "XOM": 0.025811,
      "T": 0.063165,
      "WFC": 0.1,
      "VZ": 0.004606,
      "CCL": 0.096783,
      "CVX": 0.017725,
      "CSCO": 0.036274,
      "KO": 0.1,
      "CMCSA": 0.048318,
      "MS": 0.019442
    }
  },
  {
    "date": "2021-05-28",
    "pre_value": 10317638.09,
    "post_value": 10317638.09,
    "cost": 0.0,
    "turnover": 0.544309,
    "old_weights": {
      "TSLA": 0.0,
      "AAPL": 0.0,
      "AMZN": 0.0,
      "NIO": 0.0,
      "BABA": 0.0,
      "MSFT": 0.010196,
      "META": 0.093683,
      "NVDA": 0.0,
      "AMD": 0.0,
      "ZM": 0.0,
      "GOOGL": 0.067579,
      "GOOG": 0.1,
      "NFLX": 0.0,
      "CRM": 0.0,
      "INTC": 0.0,
      "XYZ": 0.005478,
      "PYPL": 0.0,
      "DIS": 0.0,
      "JPM": 0.005686,
      "PLUG": 0.0,
      "PFE": 0.080768,
      "PLTR": 0.0,
      "BAC": 0.1,
      "SHOP": 0.0,
      "SNOW": 0.0,
      "C": 0.0,
      "XOM": 0.025811,
      "MU": 0.0,
      "T": 0.063165,
      "AAL": 0.0,
      "QCOM": 0.0,
      "UBER": 0.0,
      "TSM": 0.0,
      "JD": 0.0,
      "WFC": 0.1,
      "WMT": 0.0,
      "SNAP": 0.0,
      "VZ": 0.004606,
      "QS": 0.0,
      "CCL": 0.096783,
      "CVX": 0.017725,
      "CSCO": 0.036274,
      "KO": 0.1,
      "CMCSA": 0.048318,
      "PINS": 0.0,
      "DKNG": 0.0,
      "DOCU": 0.0,
      "UAL": 0.0,
      "NKE": 0.0,
      "MS": 0.019442
    },
    "new_weights": {
      "META": 0.098875,
      "NVDA": 0.025374,
      "GOOGL": 0.016045,
      "GOOG": 0.046149,
      "CRM": 0.025182,
      "PFE": 0.1,
      "BAC": 0.082459,
      "C": 0.033151,
      "T": 0.034045,
      "WFC": 0.1,
      "WMT": 0.045555,
      "CCL": 0.01284,
      "CSCO": 0.050363,
      "KO": 0.096225,
      "MS": 0.038391
    }
  },
  {
    "date": "2021-06-30",
    "pre_value": 10364185.13,
    "post_value": 10364185.13,
    "cost": 0.0,
    "turnover": 0.844958,
    "old_weights": {
      "TSLA": 0.0,
      "AAPL": 0.0,
      "AMZN": 0.0,
      "NIO": 0.0,
      "BABA": 0.0,
      "MSFT": 0.0,
      "META": 0.098875,
      "NVDA": 0.025374,
      "AMD": 0.0,
      "ZM": 0.0,
      "GOOGL": 0.016045,
      "GOOG": 0.046149,
      "NFLX": 0.0,
      "CRM": 0.025182,
      "INTC": 0.0,
      "XYZ": 0.0,
      "PYPL": 0.0,
      "DIS": 0.0,
      "JPM": 0.0,
      "PLUG": 0.0,
      "PFE": 0.1,
      "PLTR": 0.0,
      "BAC": 0.082459,
      "SHOP": 0.0,
      "SNOW": 0.0,
      "C": 0.033151,
      "XOM": 0.0,
      "MU": 0.0,
      "T": 0.034045,
      "AAL": 0.0,
      "QCOM": 0.0,
      "UBER": 0.0,
      "TSM": 0.0,
      "JD": 0.0,
      "WFC": 0.1,
      "WMT": 0.045555,
      "SNAP": 0.0,
      "VZ": 0.0,
      "QS": 0.0,
      "CCL": 0.01284,
      "CVX": 0.0,
      "CSCO": 0.050363,
      "KO": 0.096225,
      "CMCSA": 0.0,
      "PINS": 0.0,
      "DKNG": 0.0,
      "DOCU": 0.0,
      "UAL": 0.0,
      "NKE": 0.0,
      "MS": 0.038391
    },
    "new_weights": {
      "NIO": 0.053674,
      "MSFT": 0.020725,
      "META": 0.028394,
      "NVDA": 0.1,
      "GOOGL": 0.008836,
      "GOOG": 0.055652,
      "PYPL": 0.008005,
      "PFE": 0.1,
      "SHOP": 0.051308,
      "XOM": 0.064566,
      "WFC": 0.088738,
      "WMT": 0.016112,
      "SNAP": 0.002362,
      "KO": 0.012716,
      "DOCU": 0.046748,
      "NKE": 0.047692,
      "MS": 0.064197
    }
  },
  {
    "date": "2021-07-30",
    "pre_value": 10524086.08,
    "post_value": 10524086.08,
    "cost": 0.0,
    "turnover": 0.671449,
    "old_weights": {
      "TSLA": 0.0,
      "AAPL": 0.0,
      "AMZN": 0.0,
      "NIO": 0.053674,
      "BABA": 0.0,
      "MSFT": 0.020725,
      "META": 0.028394,
      "NVDA": 0.1,
      "AMD": 0.0,
      "ZM": 0.0,
      "GOOGL": 0.008836,
      "GOOG": 0.055652,
      "NFLX": 0.0,
      "CRM": 0.0,
      "INTC": 0.0,
      "XYZ": 0.0,
      "PYPL": 0.008005,
      "DIS": 0.0,
      "JPM": 0.0,
      "PLUG": 0.0,
      "PFE": 0.1,
      "PLTR": 0.0,
      "BAC": 0.0,
      "SHOP": 0.051308,
      "SNOW": 0.0,
      "C": 0.0,
      "XOM": 0.064566,
      "MU": 0.0,
      "T": 0.0,
      "AAL": 0.0,
      "QCOM": 0.0,
      "UBER": 0.0,
      "TSM": 0.0,
      "JD": 0.0,
      "WFC": 0.088738,
      "WMT": 0.016112,
      "SNAP": 0.002362,
      "VZ": 0.0,
      "QS": 0.0,
      "CCL": 0.0,
      "CVX": 0.0,
      "CSCO": 0.0,
      "KO": 0.012716,
      "CMCSA": 0.0,
      "PINS": 0.0,
      "DKNG": 0.0,
      "DOCU": 0.046748,
      "UAL": 0.0,
      "NKE": 0.047692,
      "MS": 0.064197
    },
    "new_weights": {
      "AAPL": 0.007135,
      "MSFT": 0.025776,
      "NVDA": 0.054897,
      "AMD": 0.094842,
      "GOOGL": 0.010851,
      "GOOG": 0.010572,
      "PFE": 0.1,
      "SHOP": 0.082816,
      "CSCO": 0.043756,
      "KO": 0.062327,
      "DOCU": 0.050824,
      "NKE": 0.1,
      "MS": 0.093311
    }
  },
  {
    "date": "2021-08-31",
    "pre_value": 10889562.21,
    "post_value": 10889562.21,
    "cost": 0.0,
    "turnover": 0.622831,
    "old_weights": {
      "TSLA": 0.0,
      "AAPL": 0.007135,
      "AMZN": 0.0,
      "NIO": 0.0,
      "BABA": 0.0,
      "MSFT": 0.025776,
      "META": 0.0,
      "NVDA": 0.054897,
      "AMD": 0.094842,
      "ZM": 0.0,
      "GOOGL": 0.010851,
      "GOOG": 0.010572,
      "NFLX": 0.0,
      "CRM": 0.0,
      "INTC": 0.0,
      "XYZ": 0.0,
      "PYPL": 0.0,
      "DIS": 0.0,
      "JPM": 0.0,
      "PLUG": 0.0,
      "PFE": 0.1,
      "PLTR": 0.0,
      "BAC": 0.0,
      "SHOP": 0.082816,
      "SNOW": 0.0,
      "C": 0.0,
      "XOM": 0.0,
      "MU": 0.0,
      "T": 0.0,
      "AAL": 0.0,
      "QCOM": 0.0,
      "UBER": 0.0,
      "TSM": 0.0,
      "JD": 0.0,
      "WFC": 0.0,
      "WMT": 0.0,
      "SNAP": 0.0,
      "VZ": 0.0,
      "QS": 0.0,
      "CCL": 0.0,
      "CVX": 0.0,
      "CSCO": 0.043756,
      "KO": 0.062327,
      "CMCSA": 0.0,
      "PINS": 0.0,
      "DKNG": 0.0,
      "DOCU": 0.050824,
      "UAL": 0.0,
      "NKE": 0.1,
      "MS": 0.093311
    },
    "new_weights": {
      "TSLA": 0.017198,
      "AAPL": 0.076259,
      "MSFT": 0.1,
      "NVDA": 0.052998,
      "AMD": 0.073646,
      "GOOGL": 0.062197,
      "GOOG": 0.082112,
      "NFLX": 0.054043,
      "PFE": 0.099516,
      "SHOP": 0.034663,
      "SNOW": 0.073186,
      "WMT": 0.003209,
      "CSCO": 0.039402,
      "CMCSA": 0.001387,
      "DOCU": 0.07843,
      "NKE": 0.090081,
      "MS": 0.061672
    }
  },
  {
    "date": "2021-09-30",
    "pre_value": 10161259.29,
    "post_value": 10161259.29,
    "cost": 0.0,
    "turnover": 0.885068,
    "old_weights": {
      "TSLA": 0.017198,
      "AAPL": 0.076259,
      "AMZN": 0.0,
      "NIO": 0.0,
      "BABA": 0.0,
      "MSFT": 0.1,
      "META": 0.0,
      "NVDA": 0.052998,
      "AMD": 0.073646,
      "ZM": 0.0,
      "GOOGL": 0.062197,
      "GOOG": 0.082112,
      "NFLX": 0.054043,
      "CRM": 0.0,
      "INTC": 0.0,
      "XYZ": 0.0,
      "PYPL": 0.0,
      "DIS": 0.0,
      "JPM": 0.0,
      "PLUG": 0.0,
      "PFE": 0.099516,
      "PLTR": 0.0,
      "BAC": 0.0,
      "SHOP": 0.034663,
      "SNOW": 0.073186,
      "C": 0.0,
      "XOM": 0.0,
      "MU": 0.0,
      "T": 0.0,
      "AAL": 0.0,
      "QCOM": 0.0,
      "UBER": 0.0,
      "TSM": 0.0,
      "JD": 0.0,
      "WFC": 0.0,
      "WMT": 0.003209,
      "SNAP": 0.0,
      "VZ": 0.0,
      "QS": 0.0,
      "CCL": 0.0,
      "CVX": 0.0,
      "CSCO": 0.039402,
      "KO": 0.0,
      "CMCSA": 0.001387,
      "PINS": 0.0,
      "DKNG": 0.0,
      "DOCU": 0.07843,
      "UAL": 0.0,
      "NKE": 0.090081,
      "MS": 0.061672
    },
    "new_weights": {
      "TSLA": 0.065443,
      "MSFT": 0.001305,
      "AMD": 0.01378,
      "GOOGL": 0.039934,
      "GOOG": 0.00497,
      "NFLX": 0.1,
      "CRM": 0.043013,
      "JPM": 0.00051,
      "PFE": 0.063943,
      "SNOW": 0.1,
      "MS": 0.011112
    }
  },
  {
    "date": "2021-10-29",
    "pre_value": 10867308.53,
    "post_value": 10867308.53,
    "cost": 0.0,
    "turnover": 0.613083,
    "old_weights": {
      "TSLA": 0.065443,
      "AAPL": 0.0,
      "AMZN": 0.0,
      "NIO": 0.0,
      "BABA": 0.0,
      "MSFT": 0.001305,
      "META": 0.0,
      "NVDA": 0.0,
      "AMD": 0.01378,
      "ZM": 0.0,
      "GOOGL": 0.039934,
      "GOOG": 0.00497,
      "NFLX": 0.1,
      "CRM": 0.043013,
      "INTC": 0.0,
      "XYZ": 0.0,
      "PYPL": 0.0,
      "DIS": 0.0,
      "JPM": 0.00051,
      "PLUG": 0.0,
      "PFE": 0.063943,
      "PLTR": 0.0,
      "BAC": 0.0,
      "SHOP": 0.0,
      "SNOW": 0.1,
      "C": 0.0,
      "XOM": 0.0,
      "MU": 0.0,
      "T": 0.0,
      "AAL": 0.0,
      "QCOM": 0.0,
      "UBER": 0.0,
      "TSM": 0.0,
      "JD": 0.0,
      "WFC": 0.0,
      "WMT": 0.0,
      "SNAP": 0.0,
      "VZ": 0.0,
      "QS": 0.0,
      "CCL": 0.0,
      "CVX": 0.0,
      "CSCO": 0.0,
      "KO": 0.0,
      "CMCSA": 0.0,
      "PINS": 0.0,
      "DKNG": 0.0,
      "DOCU": 0.0,
      "UAL": 0.0,
      "NKE": 0.0,
      "MS": 0.011112
    },
    "new_weights": {
      "TSLA": 0.1,
      "MSFT": 0.075861,
      "NVDA": 0.034043,
      "NFLX": 0.1,
      "CRM": 0.1,
      "JPM": 0.028192,
      "PLUG": 0.051625,
      "BAC": 0.1,
      "SNOW": 0.08533,
      "XOM": 0.021758,
      "WFC": 0.005199,
      "WMT": 0.018431,
      "CVX": 0.039836
    }
  },
  {
    "date": "2021-11-30",
    "pre_value": 10768732.35,
    "post_value": 10768732.35,
    "cost": 0.0,
    "turnover": 0.770422,
    "old_weights": {
      "TSLA": 0.1,
      "AAPL": 0.0,
      "AMZN": 0.0,
      "NIO": 0.0,
      "BABA": 0.0,
      "MSFT": 0.075861,
      "META": 0.0,
      "NVDA": 0.034043,
      "AMD": 0.0,
      "ZM": 0.0,
      "GOOGL": 0.0,
      "GOOG": 0.0,
      "NFLX": 0.1,
      "CRM": 0.1,
      "INTC": 0.0,
      "XYZ": 0.0,
      "PYPL": 0.0,
      "DIS": 0.0,
      "JPM": 0.028192,
      "PLUG": 0.051625,
      "PFE": 0.0,
      "PLTR": 0.0,
      "BAC": 0.1,
      "SHOP": 0.0,
      "SNOW": 0.08533,
      "C": 0.0,
      "XOM": 0.021758,
      "MU": 0.0,
      "T": 0.0,
      "AAL": 0.0,
      "QCOM": 0.0,
      "UBER": 0.0,
      "TSM": 0.0,
      "JD": 0.0,
      "WFC": 0.005199,
      "WMT": 0.018431,
      "SNAP": 0.0,
      "VZ": 0.0,
      "QS": 0.0,
      "CCL": 0.0,
      "CVX": 0.039836,
      "CSCO": 0.0,
      "KO": 0.0,
      "CMCSA": 0.0,
      "PINS": 0.0,
      "DKNG": 0.0,
      "DOCU": 0.0,
      "UAL": 0.0,
      "NKE": 0.0,
      "MS": 0.0
    },
    "new_weights": {
      "TSLA": 0.1,
      "NVDA": 0.082642,
      "AMD": 0.078189,
      "NFLX": 0.059971,
      "PLUG": 0.041493,
      "PFE": 0.1,
      "XOM": 0.029758,
      "QCOM": 0.012295,
      "CVX": 0.1
    }
  },
  {
    "date": "2021-12-31",
    "pre_value": 10527751.36,
    "post_value": 10527751.36,
    "cost": 0.0,
    "turnover": 0.797419,
    "old_weights": {
      "TSLA": 0.1,
      "AAPL": 0.0,
      "AMZN": 0.0,
      "NIO": 0.0,
      "BABA": 0.0,
      "MSFT": 0.0,
      "META": 0.0,
      "NVDA": 0.082642,
      "AMD": 0.078189,
      "ZM": 0.0,
      "GOOGL": 0.0,
      "GOOG": 0.0,
      "NFLX": 0.059971,
      "CRM": 0.0,
      "INTC": 0.0,
      "XYZ": 0.0,
      "PYPL": 0.0,
      "DIS": 0.0,
      "JPM": 0.0,
      "PLUG": 0.041493,
      "PFE": 0.1,
      "PLTR": 0.0,
      "BAC": 0.0,
      "SHOP": 0.0,
      "SNOW": 0.0,
      "C": 0.0,
      "XOM": 0.029758,
      "MU": 0.0,
      "T": 0.0,
      "AAL": 0.0,
      "QCOM": 0.012295,
      "UBER": 0.0,
      "TSM": 0.0,
      "JD": 0.0,
      "WFC": 0.0,
      "WMT": 0.0,
      "SNAP": 0.0,
      "VZ": 0.0,
      "QS": 0.0,
      "CCL": 0.0,
      "CVX": 0.1,
      "CSCO": 0.0,
      "KO": 0.0,
      "CMCSA": 0.0,
      "PINS": 0.0,
      "DKNG": 0.0,
      "DOCU": 0.0,
      "UAL": 0.0,
      "NKE": 0.0,
      "MS": 0.0
    },
    "new_weights": {
      "TSLA": 0.051106,
      "AAPL": 0.093047,
      "MSFT": 0.013065,
      "AMD": 0.034827,
      "PFE": 0.1,
      "MU": 0.067641,
      "QCOM": 0.087938,
      "WMT": 0.028716,
      "CVX": 0.086251,
      "CSCO": 0.077872,
      "KO": 0.1,
      "NKE": 0.021566
    }
  },
  {
    "date": "2022-01-31",
    "pre_value": 10159819.12,
    "post_value": 10159819.12,
    "cost": 0.0,
    "turnover": 0.508751,
    "old_weights": {
      "TSLA": 0.051106,
      "AAPL": 0.093047,
      "AMZN": 0.0,
      "NIO": 0.0,
      "BABA": 0.0,
      "MSFT": 0.013065,
      "META": 0.0,
      "NVDA": 0.0,
      "AMD": 0.034827,
      "ZM": 0.0,
      "GOOGL": 0.0,
      "GOOG": 0.0,
      "NFLX": 0.0,
      "CRM": 0.0,
      "INTC": 0.0,
      "XYZ": 0.0,
      "PYPL": 0.0,
      "DIS": 0.0,
      "JPM": 0.0,
      "PLUG": 0.0,
      "PFE": 0.1,
      "PLTR": 0.0,
      "BAC": 0.0,
      "SHOP": 0.0,
      "SNOW": 0.0,
      "C": 0.0,
      "XOM": 0.0,
      "MU": 0.067641,
      "T": 0.0,
      "AAL": 0.0,
      "QCOM": 0.087938,
      "UBER": 0.0,
      "TSM": 0.0,
      "JD": 0.0,
      "WFC": 0.0,
      "WMT": 0.028716,
      "SNAP": 0.0,
      "VZ": 0.0,
      "QS": 0.0,
      "CCL": 0.0,
      "CVX": 0.086251,
      "CSCO": 0.077872,
      "KO": 0.1,
      "CMCSA": 0.0,
      "PINS": 0.0,
      "DKNG": 0.0,
      "DOCU": 0.0,
      "UAL": 0.0,
      "NKE": 0.021566,
      "MS": 0.0
    },
    "new_weights": {
      "AAPL": 0.1,
      "PFE": 0.1,
      "QCOM": 0.005804,
      "MU": 0.049382,
      "XOM": 0.1,
      "T": 0.013451,
      "CVX": 0.1,
      "VZ": 0.014782,
      "KO": 0.06773
    }
  },
  {
    "date": "2022-02-28",
    "pre_value": 10197532.6,
    "post_value": 10197532.6,
    "cost": 0.0,
    "turnover": 0.302785,
    "old_weights": {
      "TSLA": 0.0,
      "AAPL": 0.1,
      "NVDA": 0.0,
      "AMZN": 0.0,
      "MSFT": 0.0,
      "AMD": 0.0,
      "META": 0.0,
      "GOOGL": 0.0,
      "GOOG": 0.0,
      "BABA": 0.0,
      "PYPL": 0.0,
      "NFLX": 0.0,
      "RIVN": 0.0,
      "PFE": 0.1,
      "F": 0.0,
      "BAC": 0.0,
      "RBLX": 0.0,
      "DIS": 0.0,
      "JPM": 0.0,
      "QCOM": 0.005804,
      "SHOP": 0.0,
      "XYZ": 0.0,
      "INTC": 0.0,
      "MU": 0.049382,
      "NIO": 0.0,
      "CRM": 0.0,
      "C": 0.0,
      "XOM": 0.1,
      "AVGO": 0.0,
      "T": 0.013451,
      "WFC": 0.0,
      "CVX": 0.1,
      "TSM": 0.0,
      "COIN": 0.0,
      "CSCO": 0.0,
      "WMT": 0.0,
      "UBER": 0.0,
      "SNOW": 0.0,
      "VZ": 0.014782,
      "AFRM": 0.0,
      "INTU": 0.0,
      "MRK": 0.0,
      "CMCSA": 0.0,
      "MS": 0.0,
      "KO": 0.06773,
      "NKE": 0.0,
      "LRCX": 0.0,
      "NOW": 0.0,
      "ZM": 0.0,
      "DOCU": 0.0
    },
    "new_weights": {
      "AAPL": 0.019069,
      "MU": 0.01648,
      "XOM": 0.1,
      "AVGO": 0.027727,
      "CVX": 0.1,
      "VZ": 0.024484,
      "KO": 0.1
    }
  },
  {
    "date": "2022-03-31",
    "pre_value": 10412081.3,
    "post_value": 10412081.3,
    "cost": 0.0,
    "turnover": 0.213765,
    "old_weights": {
      "TSLA": 0.0,
      "AAPL": 0.019069,
      "NVDA": 0.0,
      "AMZN": 0.0,
      "MSFT": 0.0,
      "AMD": 0.0,
      "META": 0.0,
      "GOOGL": 0.0,
      "GOOG": 0.0,
      "BABA": 0.0,
      "PYPL": 0.0,
      "NFLX": 0.0,
      "RIVN": 0.0,
      "PFE": 0.0,
      "F": 0.0,
      "BAC": 0.0,
      "RBLX": 0.0,
      "DIS": 0.0,
      "JPM": 0.0,
      "QCOM": 0.0,
      "SHOP": 0.0,
      "XYZ": 0.0,
      "INTC": 0.0,
      "MU": 0.01648,
      "NIO": 0.0,
      "CRM": 0.0,
      "C": 0.0,
      "XOM": 0.1,
      "AVGO": 0.027727,
      "T": 0.0,
      "WFC": 0.0,
      "CVX": 0.1,
      "TSM": 0.0,
      "COIN": 0.0,
      "CSCO": 0.0,
      "WMT": 0.0,
      "UBER": 0.0,
      "SNOW": 0.0,
      "VZ": 0.024484,
      "AFRM": 0.0,
      "INTU": 0.0,
      "MRK": 0.0,
      "CMCSA": 0.0,
      "MS": 0.0,
      "KO": 0.1,
      "NKE": 0.0,
      "LRCX": 0.0,
      "NOW": 0.0,
      "ZM": 0.0,
      "DOCU": 0.0
    },
    "new_weights": {
      "TSLA": 0.020565,
      "XOM": 0.1,
      "CVX": 0.1,
      "WMT": 0.047413,
      "MRK": 0.043818,
      "KO": 0.085791
    }
  },
  {
    "date": "2022-04-29",
    "pre_value": 10466480.97,
    "post_value": 10466480.97,
    "cost": 0.0,
    "turnover": 0.145234,
    "old_weights": {
      "TSLA": 0.020565,
      "AAPL": 0.0,
      "NVDA": 0.0,
      "AMZN": 0.0,
      "MSFT": 0.0,
      "AMD": 0.0,
      "META": 0.0,
      "GOOGL": 0.0,
      "GOOG": 0.0,
      "BABA": 0.0,
      "PYPL": 0.0,
      "NFLX": 0.0,
      "RIVN": 0.0,
      "PFE": 0.0,
      "F": 0.0,
      "BAC": 0.0,
      "RBLX": 0.0,
      "DIS": 0.0,
      "JPM": 0.0,
      "QCOM": 0.0,
      "SHOP": 0.0,
      "XYZ": 0.0,
      "INTC": 0.0,
      "MU": 0.0,
      "NIO": 0.0,
      "CRM": 0.0,
      "C": 0.0,
      "XOM": 0.1,
      "AVGO": 0.0,
      "T": 0.0,
      "WFC": 0.0,
      "CVX": 0.1,
      "TSM": 0.0,
      "COIN": 0.0,
      "CSCO": 0.0,
      "WMT": 0.047413,
      "UBER": 0.0,
      "SNOW": 0.0,
      "VZ": 0.0,
      "AFRM": 0.0,
      "INTU": 0.0,
      "MRK": 0.043818,
      "CMCSA": 0.0,
      "MS": 0.0,
      "KO": 0.085791,
      "NKE": 0.0,
      "LRCX": 0.0,
      "NOW": 0.0,
      "ZM": 0.0,
      "DOCU": 0.0
    },
    "new_weights": {
      "TSLA": 0.017343,
      "XOM": 0.030677,
      "CVX": 0.1,
      "WMT": 0.081456,
      "MRK": 0.05702,
      "KO": 0.060348
    }
  },
  {
    "date": "2022-05-31",
    "pre_value": 10505105.75,
    "post_value": 10505105.75,
    "cost": 0.0,
    "turnover": 0.4943,
    "old_weights": {
      "TSLA": 0.017343,
      "AAPL": 0.0,
      "NVDA": 0.0,
      "AMZN": 0.0,
      "MSFT": 0.0,
      "AMD": 0.0,
      "META": 0.0,
      "GOOGL": 0.0,
      "GOOG": 0.0,
      "BABA": 0.0,
      "PYPL": 0.0,
      "NFLX": 0.0,
      "RIVN": 0.0,
      "PFE": 0.0,
      "F": 0.0,
      "BAC": 0.0,
      "RBLX": 0.0,
      "DIS": 0.0,
      "JPM": 0.0,
      "QCOM": 0.0,
      "SHOP": 0.0,
      "XYZ": 0.0,
      "INTC": 0.0,
      "MU": 0.0,
      "NIO": 0.0,
      "CRM": 0.0,
      "C": 0.0,
      "XOM": 0.030677,
      "AVGO": 0.0,
      "T": 0.0,
      "WFC": 0.0,
      "CVX": 0.1,
      "TSM": 0.0,
      "COIN": 0.0,
      "CSCO": 0.0,
      "WMT": 0.081456,
      "UBER": 0.0,
      "SNOW": 0.0,
      "VZ": 0.0,
      "AFRM": 0.0,
      "INTU": 0.0,
      "MRK": 0.05702,
      "CMCSA": 0.0,
      "MS": 0.0,
      "KO": 0.060348,
      "NKE": 0.0,
      "LRCX": 0.0,
      "NOW": 0.0,
      "ZM": 0.0,
      "DOCU": 0.0
    },
    "new_weights": {
      "BABA": 0.002223,
      "PFE": 0.082771,
      "XOM": 0.070431,
      "T": 0.1,
      "CVX": 0.032573,
      "MRK": 0.1
    }
  },
  {
    "date": "2022-06-30",
    "pre_value": 10361449.28,
    "post_value": 10361449.28,
    "cost": 0.0,
    "turnover": 0.209215,
    "old_weights": {
      "TSLA": 0.0,
      "AAPL": 0.0,
      "NVDA": 0.0,
      "AMZN": 0.0,
      "MSFT": 0.0,
      "AMD": 0.0,
      "META": 0.0,
      "GOOGL": 0.0,
      "GOOG": 0.0,
      "BABA": 0.002223,
      "PYPL": 0.0,
      "NFLX": 0.0,
      "RIVN": 0.0,
      "PFE": 0.082771,
      "F": 0.0,
      "BAC": 0.0,
      "RBLX": 0.0,
      "DIS": 0.0,
      "JPM": 0.0,
      "QCOM": 0.0,
      "SHOP": 0.0,
      "XYZ": 0.0,
      "INTC": 0.0,
      "MU": 0.0,
      "NIO": 0.0,
      "CRM": 0.0,
      "C": 0.0,
      "XOM": 0.070431,
      "AVGO": 0.0,
      "T": 0.1,
      "WFC": 0.0,
      "CVX": 0.032573,
      "TSM": 0.0,
      "COIN": 0.0,
      "CSCO": 0.0,
      "WMT": 0.0,
      "UBER": 0.0,
      "SNOW": 0.0,
      "VZ": 0.0,
      "AFRM": 0.0,
      "INTU": 0.0,
      "MRK": 0.1,
      "CMCSA": 0.0,
      "MS": 0.0,
      "KO": 0.0,
      "NKE": 0.0,
      "LRCX": 0.0,
      "NOW": 0.0,
      "ZM": 0.0,
      "DOCU": 0.0
    },
    "new_weights": {
      "XOM": 0.002,
      "T": 0.096952,
      "MRK": 0.07983
    }
  },
  {
    "date": "2022-07-29",
    "pre_value": 10268938.77,
    "post_value": 10268938.77,
    "cost": 0.0,
    "turnover": 0.247738,
    "old_weights": {
      "TSLA": 0.0,
      "AAPL": 0.0,
      "NVDA": 0.0,
      "AMZN": 0.0,
      "MSFT": 0.0,
      "AMD": 0.0,
      "META": 0.0,
      "GOOGL": 0.0,
      "GOOG": 0.0,
      "BABA": 0.0,
      "PYPL": 0.0,
      "NFLX": 0.0,
      "RIVN": 0.0,
      "PFE": 0.0,
      "F": 0.0,
      "BAC": 0.0,
      "RBLX": 0.0,
      "DIS": 0.0,
      "JPM": 0.0,
      "QCOM": 0.0,
      "SHOP": 0.0,
      "XYZ": 0.0,
      "INTC": 0.0,
      "MU": 0.0,
      "NIO": 0.0,
      "CRM": 0.0,
      "C": 0.0,
      "XOM": 0.002,
      "AVGO": 0.0,
      "T": 0.096952,
      "WFC": 0.0,
      "CVX": 0.0,
      "TSM": 0.0,
      "COIN": 0.0,
      "CSCO": 0.0,
      "WMT": 0.0,
      "UBER": 0.0,
      "SNOW": 0.0,
      "VZ": 0.0,
      "AFRM": 0.0,
      "INTU": 0.0,
      "MRK": 0.07983,
      "CMCSA": 0.0,
      "MS": 0.0,
      "KO": 0.0,
      "NKE": 0.0,
      "LRCX": 0.0,
      "NOW": 0.0,
      "ZM": 0.0,
      "DOCU": 0.0
    },
    "new_weights": {
      "RBLX": 0.029259,
      "NIO": 0.002955,
      "XOM": 0.044767,
      "MRK": 0.004024
    }
  },
  {
    "date": "2022-08-31",
    "pre_value": 10259804.25,
    "post_value": 10259804.25,
    "cost": 0.0,
    "turnover": 0.13509,
    "old_weights": {
      "TSLA": 0.0,
      "AAPL": 0.0,
      "NVDA": 0.0,
      "AMZN": 0.0,
      "MSFT": 0.0,
      "AMD": 0.0,
      "META": 0.0,
      "GOOGL": 0.0,
      "GOOG": 0.0,
      "BABA": 0.0,
      "PYPL": 0.0,
      "NFLX": 0.0,
      "RIVN": 0.0,
      "PFE": 0.0,
      "F": 0.0,
      "BAC": 0.0,
      "RBLX": 0.029259,
      "DIS": 0.0,
      "JPM": 0.0,
      "QCOM": 0.0,
      "SHOP": 0.0,
      "XYZ": 0.0,
      "INTC": 0.0,
      "MU": 0.0,
      "NIO": 0.002955,
      "CRM": 0.0,
      "C": 0.0,
      "XOM": 0.044767,
      "AVGO": 0.0,
      "T": 0.0,
      "WFC": 0.0,
      "CVX": 0.0,
      "TSM": 0.0,
      "COIN": 0.0,
      "CSCO": 0.0,
      "WMT": 0.0,
      "UBER": 0.0,
      "SNOW": 0.0,
      "VZ": 0.0,
      "AFRM": 0.0,
      "INTU": 0.0,
      "MRK": 0.004024,
      "CMCSA": 0.0,
      "MS": 0.0,
      "KO": 0.0,
      "NKE": 0.0,
      "LRCX": 0.0,
      "NOW": 0.0,
      "ZM": 0.0,
      "DOCU": 0.0
    },
    "new_weights": {
      "F": 0.000838,
      "RBLX": 0.018082,
      "WMT": 0.017065,
      "UBER": 0.015289,
      "SNOW": 0.038977
    }
  },
  {
    "date": "2022-09-30",
    "pre_value": 10224458.89,
    "post_value": 10224458.89,
    "cost": 0.0,
    "turnover": 0.191556,
    "old_weights": {
      "TSLA": 0.0,
      "AAPL": 0.0,
      "NVDA": 0.0,
      "AMZN": 0.0,
      "MSFT": 0.0,
      "AMD": 0.0,
      "META": 0.0,
      "GOOGL": 0.0,
      "GOOG": 0.0,
      "BABA": 0.0,
      "PYPL": 0.0,
      "NFLX": 0.0,
      "RIVN": 0.0,
      "PFE": 0.0,
      "F": 0.000838,
      "BAC": 0.0,
      "RBLX": 0.018082,
      "DIS": 0.0,
      "JPM": 0.0,
      "QCOM": 0.0,
      "SHOP": 0.0,
      "XYZ": 0.0,
      "INTC": 0.0,
      "MU": 0.0,
      "NIO": 0.0,
      "CRM": 0.0,
      "C": 0.0,
      "XOM": 0.0,
      "AVGO": 0.0,
      "T": 0.0,
      "WFC": 0.0,
      "CVX": 0.0,
      "TSM": 0.0,
      "COIN": 0.0,
      "CSCO": 0.0,
      "WMT": 0.017065,
      "UBER": 0.015289,
      "SNOW": 0.038977,
      "VZ": 0.0,
      "AFRM": 0.0,
      "INTU": 0.0,
      "MRK": 0.0,
      "CMCSA": 0.0,
      "MS": 0.0,
      "KO": 0.0,
      "NKE": 0.0,
      "LRCX": 0.0,
      "NOW": 0.0,
      "ZM": 0.0,
      "DOCU": 0.0
    },
    "new_weights": {
      "NFLX": 0.066902,
      "RIVN": 0.049484,
      "WMT": 0.006046,
      "UBER": 0.021543
    }
  },
  {
    "date": "2022-10-31",
    "pre_value": 10457673.13,
    "post_value": 10457673.13,
    "cost": 0.0,
    "turnover": 0.279658,
    "old_weights": {
      "TSLA": 0.0,
      "AAPL": 0.0,
      "NVDA": 0.0,
      "AMZN": 0.0,
      "MSFT": 0.0,
      "AMD": 0.0,
      "META": 0.0,
      "GOOGL": 0.0,
      "GOOG": 0.0,
      "BABA": 0.0,
      "PYPL": 0.0,
      "NFLX": 0.066902,
      "RIVN": 0.049484,
      "PFE": 0.0,
      "F": 0.0,
      "BAC": 0.0,
      "RBLX": 0.0,
      "DIS": 0.0,
      "JPM": 0.0,
      "QCOM": 0.0,
      "SHOP": 0.0,
      "XYZ": 0.0,
      "INTC": 0.0,
      "MU": 0.0,
      "NIO": 0.0,
      "CRM": 0.0,
      "C": 0.0,
      "XOM": 0.0,
      "AVGO": 0.0,
      "T": 0.0,
      "WFC": 0.0,
      "CVX": 0.0,
      "TSM": 0.0,
      "COIN": 0.0,
      "CSCO": 0.0,
      "WMT": 0.006046,
      "UBER": 0.021543,
      "SNOW": 0.0,
      "VZ": 0.0,
      "AFRM": 0.0,
      "INTU": 0.0,
      "MRK": 0.0,
      "CMCSA": 0.0,
      "MS": 0.0,
      "KO": 0.0,
      "NKE": 0.0,
      "LRCX": 0.0,
      "NOW": 0.0,
      "ZM": 0.0,
      "DOCU": 0.0
    },
    "new_weights": {
      "NFLX": 0.05567,
      "JPM": 0.009843,
      "XOM": 0.062628,
      "CVX": 0.016498,
      "WMT": 0.014476,
      "MRK": 0.1
    }
  },
  {
    "date": "2022-11-30",
    "pre_value": 10631136.42,
    "post_value": 10631136.42,
    "cost": 0.0,
    "turnover": 0.166936,
    "old_weights": {
      "TSLA": 0.0,
      "AAPL": 0.0,
      "NVDA": 0.0,
      "AMZN": 0.0,
      "MSFT": 0.0,
      "AMD": 0.0,
      "META": 0.0,
      "GOOGL": 0.0,
      "GOOG": 0.0,
      "BABA": 0.0,
      "PYPL": 0.0,
      "NFLX": 0.05567,
      "RIVN": 0.0,
      "PFE": 0.0,
      "F": 0.0,
      "BAC": 0.0,
      "RBLX": 0.0,
      "DIS": 0.0,
      "JPM": 0.009843,
      "QCOM": 0.0,
      "SHOP": 0.0,
      "XYZ": 0.0,
      "INTC": 0.0,
      "MU": 0.0,
      "NIO": 0.0,
      "CRM": 0.0,
      "C": 0.0,
      "XOM": 0.062628,
      "AVGO": 0.0,
      "T": 0.0,
      "WFC": 0.0,
      "CVX": 0.016498,
      "TSM": 0.0,
      "COIN": 0.0,
      "CSCO": 0.0,
      "WMT": 0.014476,
      "UBER": 0.0,
      "SNOW": 0.0,
      "VZ": 0.0,
      "AFRM": 0.0,
      "INTU": 0.0,
      "MRK": 0.1,
      "CMCSA": 0.0,
      "MS": 0.0,
      "KO": 0.0,
      "NKE": 0.0,
      "LRCX": 0.0,
      "NOW": 0.0,
      "ZM": 0.0,
      "DOCU": 0.0
    },
    "new_weights": {
      "NFLX": 0.04207,
      "PFE": 0.013248,
      "JPM": 0.059191,
      "SHOP": 0.008508,
      "XOM": 0.039526,
      "CVX": 0.013299,
      "WMT": 0.070408,
      "MRK": 0.1
    }
  },
  {
    "date": "2022-12-30",
    "pre_value": 10561245.86,
    "post_value": 10561245.86,
    "cost": 0.0,
    "turnover": 0.395279,
    "old_weights": {
      "TSLA": 0.0,
      "AAPL": 0.0,
      "NVDA": 0.0,
      "AMZN": 0.0,
      "MSFT": 0.0,
      "AMD": 0.0,
      "META": 0.0,
      "GOOGL": 0.0,
      "GOOG": 0.0,
      "BABA": 0.0,
      "PYPL": 0.0,
      "NFLX": 0.04207,
      "RIVN": 0.0,
      "PFE": 0.013248,
      "F": 0.0,
      "BAC": 0.0,
      "RBLX": 0.0,
      "DIS": 0.0,
      "JPM": 0.059191,
      "QCOM": 0.0,
      "SHOP": 0.008508,
      "XYZ": 0.0,
      "INTC": 0.0,
      "MU": 0.0,
      "NIO": 0.0,
      "CRM": 0.0,
      "C": 0.0,
      "XOM": 0.039526,
      "AVGO": 0.0,
      "T": 0.0,
      "WFC": 0.0,
      "CVX": 0.013299,
      "TSM": 0.0,
      "COIN": 0.0,
      "CSCO": 0.0,
      "WMT": 0.070408,
      "UBER": 0.0,
      "SNOW": 0.0,
      "VZ": 0.0,
      "AFRM": 0.0,
      "INTU": 0.0,
      "MRK": 0.1,
      "CMCSA": 0.0,
      "MS": 0.0,
      "KO": 0.0,
      "NKE": 0.0,
      "LRCX": 0.0,
      "NOW": 0.0,
      "ZM": 0.0,
      "DOCU": 0.0
    },
    "new_weights": {
      "PFE": 0.034363,
      "JPM": 0.080614,
      "XOM": 0.072591,
      "T": 0.069686,
      "CVX": 0.039869,
      "CSCO": 0.002894,
      "MRK": 0.1,
      "KO": 0.022441,
      "NKE": 0.0771
    }
  },
  {
    "date": "2023-01-31",
    "pre_value": 10710494.06,
    "post_value": 10710494.06,
    "cost": 0.0,
    "turnover": 0.756536,
    "old_weights": {
      "TSLA": 0.0,
      "AAPL": 0.0,
      "NVDA": 0.0,
      "AMZN": 0.0,
      "MSFT": 0.0,
      "AMD": 0.0,
      "META": 0.0,
      "GOOGL": 0.0,
      "GOOG": 0.0,
      "BABA": 0.0,
      "PYPL": 0.0,
      "NFLX": 0.0,
      "RIVN": 0.0,
      "PFE": 0.034363,
      "F": 0.0,
      "BAC": 0.0,
      "RBLX": 0.0,
      "DIS": 0.0,
      "JPM": 0.080614,
      "QCOM": 0.0,
      "SHOP": 0.0,
      "XYZ": 0.0,
      "INTC": 0.0,
      "MU": 0.0,
      "NIO": 0.0,
      "CRM": 0.0,
      "C": 0.0,
      "XOM": 0.072591,
      "AVGO": 0.0,
      "T": 0.069686,
      "WFC": 0.0,
      "CVX": 0.039869,
      "TSM": 0.0,
      "COIN": 0.0,
      "CSCO": 0.002894,
      "WMT": 0.0,
      "UBER": 0.0,
      "SNOW": 0.0,
      "VZ": 0.0,
      "AFRM": 0.0,
      "INTU": 0.0,
      "MRK": 0.1,
      "CMCSA": 0.0,
      "MS": 0.0,
      "KO": 0.022441,
      "NKE": 0.0771,
      "LRCX": 0.0,
      "NOW": 0.0,
      "ZM": 0.0,
      "DOCU": 0.0
    },
    "new_weights": {
      "META": 0.063434,
      "BABA": 0.075383,
      "TSM": 0.088037,
      "MRK": 0.052289,
      "VZ": 0.052458,
      "NKE": 0.013405,
      "CMCSA": 0.024286,
      "T": 0.025051,
      "SBUX": 0.030412,
      "MS": 0.013713
    }
  },
  {
    "date": "2023-02-28",
    "pre_value": 10505897.43,
    "post_value": 10505897.43,
    "cost": 0.0,
    "turnover": 0.430497,
    "old_weights": {
      "TSLA": 0.0,
      "AAPL": 0.0,
      "AMZN": 0.0,
      "NVDA": 0.0,
      "MSFT": 0.0,
      "AMD": 0.0,
      "META": 0.063434,
      "GOOGL": 0.0,
      "NFLX": 0.0,
      "GOOG": 0.0,
      "BABA": 0.075383,
      "XOM": 0.0,
      "CVX": 0.0,
      "DIS": 0.0,
      "CRM": 0.0,
      "JPM": 0.0,
      "BAC": 0.0,
      "AVGO": 0.0,
      "TSM": 0.088037,
      "PYPL": 0.0,
      "INTC": 0.0,
      "PFE": 0.0,
      "QCOM": 0.0,
      "MRK": 0.052289,
      "VZ": 0.052458,
      "WMT": 0.0,
      "NKE": 0.013405,
      "MU": 0.0,
      "CSCO": 0.0,
      "C": 0.0,
      "SHOP": 0.0,
      "XYZ": 0.0,
      "OXY": 0.0,
      "CMCSA": 0.024286,
      "WFC": 0.0,
      "PEP": 0.0,
      "SNOW": 0.0,
      "KO": 0.0,
      "COIN": 0.0,
      "T": 0.025051,
      "CVS": 0.0,
      "INTU": 0.0,
      "LRCX": 0.0,
      "F": 0.0,
      "SBUX": 0.030412,
      "BMY": 0.0,
      "NOW": 0.0,
      "MS": 0.013713,
      "NIO": 0.0,
      "SCHW": 0.0
    },
    "new_weights": {
      "NVDA": 0.053451,
      "META": 0.095516,
      "BABA": 0.019389,
      "JPM": 0.008803,
      "MRK": 0.011463,
      "NKE": 0.008023
    }
  },
  {
    "date": "2023-03-31",
    "pre_value": 10859831.84,
    "post_value": 10859831.84,
    "cost": 0.0,
    "turnover": 0.32444,
    "old_weights": {
      "TSLA": 0.0,
      "AAPL": 0.0,
      "AMZN": 0.0,
      "NVDA": 0.053451,
      "MSFT": 0.0,
      "AMD": 0.0,
      "META": 0.095516,
      "GOOGL": 0.0,
      "NFLX": 0.0,
      "GOOG": 0.0,
      "BABA": 0.019389,
      "XOM": 0.0,
      "CVX": 0.0,
      "DIS": 0.0,
      "CRM": 0.0,
      "JPM": 0.008803,
      "BAC": 0.0,
      "AVGO": 0.0,
      "TSM": 0.0,
      "PYPL": 0.0,
      "INTC": 0.0,
      "PFE": 0.0,
      "QCOM": 0.0,
      "MRK": 0.011463,
      "VZ": 0.0,
      "WMT": 0.0,
      "NKE": 0.008023,
      "MU": 0.0,
      "CSCO": 0.0,
      "C": 0.0,
      "SHOP": 0.0,
      "XYZ": 0.0,
      "OXY": 0.0,
      "CMCSA": 0.0,
      "WFC": 0.0,
      "PEP": 0.0,
      "SNOW": 0.0,
      "KO": 0.0,
      "COIN": 0.0,
      "T": 0.0,
      "CVS": 0.0,
      "INTU": 0.0,
      "LRCX": 0.0,
      "F": 0.0,
      "SBUX": 0.0,
      "BMY": 0.0,
      "NOW": 0.0,
      "MS": 0.0,
      "NIO": 0.0,
      "SCHW": 0.0
    },
    "new_weights": {
      "TSLA": 0.041383,
      "AAPL": 0.04586,
      "NVDA": 0.1,
      "META": 0.091313,
      "CRM": 0.1,
      "MRK": 0.009129,
      "WMT": 0.009343,
      "CSCO": 0.008152,
      "T": 0.0304
    }
  },
  {
    "date": "2023-04-28",
    "pre_value": 10892664.86,
    "post_value": 10892664.86,
    "cost": 0.0,
    "turnover": 0.521844,
    "old_weights": {
      "TSLA": 0.041383,
      "AAPL": 0.04586,
      "AMZN": 0.0,
      "NVDA": 0.1,
      "MSFT": 0.0,
      "AMD": 0.0,
      "META": 0.091313,
      "GOOGL": 0.0,
      "NFLX": 0.0,
      "GOOG": 0.0,
      "BABA": 0.0,
      "XOM": 0.0,
      "CVX": 0.0,
      "DIS": 0.0,
      "CRM": 0.1,
      "JPM": 0.0,
      "BAC": 0.0,
      "AVGO": 0.0,
      "TSM": 0.0,
      "PYPL": 0.0,
      "INTC": 0.0,
      "PFE": 0.0,
      "QCOM": 0.0,
      "MRK": 0.009129,
      "VZ": 0.0,
      "WMT": 0.009343,
      "NKE": 0.0,
      "MU": 0.0,
      "CSCO": 0.008152,
      "C": 0.0,
      "SHOP": 0.0,
      "XYZ": 0.0,
      "OXY": 0.0,
      "CMCSA": 0.0,
      "WFC": 0.0,
      "PEP": 0.0,
      "SNOW": 0.0,
      "KO": 0.0,
      "COIN": 0.0,
      "T": 0.0304,
      "CVS": 0.0,
      "INTU": 0.0,
      "LRCX": 0.0,
      "F": 0.0,
      "SBUX": 0.0,
      "BMY": 0.0,
      "NOW": 0.0,
      "MS": 0.0,
      "NIO": 0.0,
      "SCHW": 0.0
    },
    "new_weights": {
      "AAPL": 0.018147,
      "NVDA": 0.068523,
      "MSFT": 0.034526,
      "META": 0.085947,
      "XOM": 0.009752,
      "CRM": 0.036583,
      "MRK": 0.092466,
      "WMT": 0.042464,
      "PEP": 0.1,
      "KO": 0.053201
    }
  },
  {
    "date": "2023-05-31",
    "pre_value": 11174159.12,
    "post_value": 11174159.12,
    "cost": 0.0,
    "turnover": 0.473216,
    "old_weights": {
      "TSLA": 0.0,
      "AAPL": 0.018147,
      "AMZN": 0.0,
      "NVDA": 0.068523,
      "MSFT": 0.034526,
      "AMD": 0.0,
      "META": 0.085947,
      "GOOGL": 0.0,
      "NFLX": 0.0,
      "GOOG": 0.0,
      "BABA": 0.0,
      "XOM": 0.009752,
      "CVX": 0.0,
      "DIS": 0.0,
      "CRM": 0.036583,
      "JPM": 0.0,
      "BAC": 0.0,
      "AVGO": 0.0,
      "TSM": 0.0,
      "PYPL": 0.0,
      "INTC": 0.0,
      "PFE": 0.0,
      "QCOM": 0.0,
      "MRK": 0.092466,
      "VZ": 0.0,
      "WMT": 0.042464,
      "NKE": 0.0,
      "MU": 0.0,
      "CSCO": 0.0,
      "C": 0.0,
      "SHOP": 0.0,
      "XYZ": 0.0,
      "OXY": 0.0,
      "CMCSA": 0.0,
      "WFC": 0.0,
      "PEP": 0.1,
      "SNOW": 0.0,
      "KO": 0.053201,
      "COIN": 0.0,
      "T": 0.0,
      "CVS": 0.0,
      "INTU": 0.0,
      "LRCX": 0.0,
      "F": 0.0,
      "SBUX": 0.0,
      "BMY": 0.0,
      "NOW": 0.0,
      "MS": 0.0,
      "NIO": 0.0,
      "SCHW": 0.0
    },
    "new_weights": {
      "AAPL": 0.012258,
      "AMZN": 0.033029,
      "NVDA": 0.079535,
      "MSFT": 0.051383,
      "AMD": 0.010057,
      "META": 0.071198,
      "GOOGL": 0.061907,
      "GOOG": 0.061515,
      "CRM": 0.053214,
      "AVGO": 0.049225,
      "INTC": 0.046089,
      "MRK": 0.065668,
      "WMT": 0.046066,
      "SHOP": 0.033866,
      "PEP": 0.085503,
      "SNOW": 0.004539
    }
  },
  {
    "date": "2023-06-30",
    "pre_value": 11581876.35,
    "post_value": 11581876.35,
    "cost": 0.0,
    "turnover": 0.663155,
    "old_weights": {
      "TSLA": 0.0,
      "AAPL": 0.012258,
      "AMZN": 0.033029,
      "NVDA": 0.079535,
      "MSFT": 0.051383,
      "AMD": 0.010057,
      "META": 0.071198,
      "GOOGL": 0.061907,
      "NFLX": 0.0,
      "GOOG": 0.061515,
      "BABA": 0.0,
      "XOM": 0.0,
      "CVX": 0.0,
      "DIS": 0.0,
      "CRM": 0.053214,
      "JPM": 0.0,
      "BAC": 0.0,
      "AVGO": 0.049225,
      "TSM": 0.0,
      "PYPL": 0.0,
      "INTC": 0.046089,
      "PFE": 0.0,
      "QCOM": 0.0,
      "MRK": 0.065668,
      "VZ": 0.0,
      "WMT": 0.046066,
      "NKE": 0.0,
      "MU": 0.0,
      "CSCO": 0.0,
      "C": 0.0,
      "SHOP": 0.033866,
      "XYZ": 0.0,
      "OXY": 0.0,
      "CMCSA": 0.0,
      "WFC": 0.0,
      "PEP": 0.085503,
      "SNOW": 0.004539,
      "KO": 0.0,
      "COIN": 0.0,
      "T": 0.0,
      "CVS": 0.0,
      "INTU": 0.0,
      "LRCX": 0.0,
      "F": 0.0,
      "SBUX": 0.0,
      "BMY": 0.0,
      "NOW": 0.0,
      "MS": 0.0,
      "NIO": 0.0,
      "SCHW": 0.0
    },
    "new_weights": {
      "AAPL": 0.029713,
      "AMZN": 0.051651,
      "NVDA": 0.068383,
      "META": 0.08132,
      "GOOGL": 0.009236,
      "NFLX": 0.04939,
      "GOOG": 0.014547,
      "JPM": 0.037029,
      "AVGO": 0.06874,
      "MRK": 0.1,
      "WMT": 0.045372,
      "SHOP": 0.053245,
      "WFC": 0.051256,
      "PEP": 0.029233,
      "SNOW": 0.022253,
      "F": 0.058903,
      "NOW": 0.000937
    }
  },
  {
    "date": "2023-07-31",
    "pre_value": 11815822.45,
    "post_value": 11815822.45,
    "cost": 0.0,
    "turnover": 0.784949,
    "old_weights": {
      "TSLA": 0.0,
      "AAPL": 0.029713,
      "AMZN": 0.051651,
      "NVDA": 0.068383,
      "MSFT": 0.0,
      "AMD": 0.0,
      "META": 0.08132,
      "GOOGL": 0.009236,
      "NFLX": 0.04939,
      "GOOG": 0.014547,
      "BABA": 0.0,
      "XOM": 0.0,
      "CVX": 0.0,
      "DIS": 0.0,
      "CRM": 0.0,
      "JPM": 0.037029,
      "BAC": 0.0,
      "AVGO": 0.06874,
      "TSM": 0.0,
      "PYPL": 0.0,
      "INTC": 0.0,
      "PFE": 0.0,
      "QCOM": 0.0,
      "MRK": 0.1,
      "VZ": 0.0,
      "WMT": 0.045372,
      "NKE": 0.0,
      "MU": 0.0,
      "CSCO": 0.0,
      "C": 0.0,
      "SHOP": 0.053245,
      "XYZ": 0.0,
      "OXY": 0.0,
      "CMCSA": 0.0,
      "WFC": 0.051256,
      "PEP": 0.029233,
      "SNOW": 0.022253,
      "KO": 0.0,
      "COIN": 0.0,
      "T": 0.0,
      "CVS": 0.0,
      "INTU": 0.0,
      "LRCX": 0.0,
      "F": 0.058903,
      "SBUX": 0.0,
      "BMY": 0.0,
      "NOW": 0.000937,
      "MS": 0.0,
      "NIO": 0.0,
      "SCHW": 0.0
    },
    "new_weights": {
      "TSLA": 0.056648,
      "AAPL": 0.01291,
      "AMZN": 0.072312,
      "NVDA": 0.074431,
      "META": 0.049948,
      "GOOGL": 0.022257,
      "NFLX": 0.006657,
      "GOOG": 0.012856,
      "JPM": 0.039925,
      "AVGO": 0.070478,
      "WMT": 0.059604,
      "SHOP": 0.009632,
      "XYZ": 0.028475,
      "CMCSA": 0.03131,
      "COIN": 0.038502,
      "LRCX": 0.020267,
      "NIO": 0.086258,
      "SCHW": 0.066096
    }
  },
  {
    "date": "2023-08-31",
    "pre_value": 11202363.9,
    "post_value": 11202363.9,
    "cost": 0.0,
    "turnover": 0.893516,
    "old_weights": {
      "TSLA": 0.056648,
      "AAPL": 0.01291,
      "AMZN": 0.072312,
      "NVDA": 0.074431,
      "MSFT": 0.0,
      "AMD": 0.0,
      "META": 0.049948,
      "GOOGL": 0.022257,
      "NFLX": 0.006657,
      "GOOG": 0.012856,
      "BABA": 0.0,
      "XOM": 0.0,
      "CVX": 0.0,
      "DIS": 0.0,
      "CRM": 0.0,
      "JPM": 0.039925,
      "BAC": 0.0,
      "AVGO": 0.070478,
      "TSM": 0.0,
      "PYPL": 0.0,
      "INTC": 0.0,
      "PFE": 0.0,
      "QCOM": 0.0,
      "MRK": 0.0,
      "VZ": 0.0,
      "WMT": 0.059604,
      "NKE": 0.0,
      "MU": 0.0,
      "CSCO": 0.0,
      "C": 0.0,
      "SHOP": 0.009632,
      "XYZ": 0.028475,
      "OXY": 0.0,
      "CMCSA": 0.03131,
      "WFC": 0.0,
      "PEP": 0.0,
      "SNOW": 0.0,
      "KO": 0.0,
      "COIN": 0.038502,
      "T": 0.0,
      "CVS": 0.0,
      "INTU": 0.0,
      "LRCX": 0.020267,
      "F": 0.0,
      "SBUX": 0.0,
      "BMY": 0.0,
      "NOW": 0.0,
      "MS": 0.0,
      "NIO": 0.086258,
      "SCHW": 0.066096
    },
    "new_weights": {
      "TSLA": 0.020251,
      "AMZN": 0.021117,
      "NVDA": 0.054709,
      "GOOGL": 0.002039,
      "GOOG": 0.004385,
      "XOM": 0.047251,
      "CVX": 0.026144,
      "JPM": 0.013383,
      "AVGO": 0.00762,
      "WMT": 0.1,
      "CSCO": 0.1,
      "OXY": 0.029584,
      "CMCSA": 0.1,
      "COIN": 0.014856,
      "INTU": 0.1,
      "NIO": 0.021281,
      "SCHW": 0.02656
    }
  },
  {
    "date": "2023-09-29",
    "pre_value": 10889705.07,
    "post_value": 10889705.07,
    "cost": 0.0,
    "turnover": 0.567928,
    "old_weights": {
      "TSLA": 0.020251,
      "AAPL": 0.0,
      "AMZN": 0.021117,
      "NVDA": 0.054709,
      "MSFT": 0.0,
      "AMD": 0.0,
      "META": 0.0,
      "GOOGL": 0.002039,
      "NFLX": 0.0,
      "GOOG": 0.004385,
      "BABA": 0.0,
      "XOM": 0.047251,
      "CVX": 0.026144,
      "DIS": 0.0,
      "CRM": 0.0,
      "JPM": 0.013383,
      "BAC": 0.0,
      "AVGO": 0.00762,
      "TSM": 0.0,
      "PYPL": 0.0,
      "INTC": 0.0,
      "PFE": 0.0,
      "QCOM": 0.0,
      "MRK": 0.0,
      "VZ": 0.0,
      "WMT": 0.1,
      "NKE": 0.0,
      "MU": 0.0,
      "CSCO": 0.1,
      "C": 0.0,
      "SHOP": 0.0,
      "XYZ": 0.0,
      "OXY": 0.029584,
      "CMCSA": 0.1,
      "WFC": 0.0,
      "PEP": 0.0,
      "SNOW": 0.0,
      "KO": 0.0,
      "COIN": 0.014856,
      "T": 0.0,
      "CVS": 0.0,
      "INTU": 0.1,
      "LRCX": 0.0,
      "F": 0.0,
      "SBUX": 0.0,
      "BMY": 0.0,
      "NOW": 0.0,
      "MS": 0.0,
      "NIO": 0.021281,
      "SCHW": 0.02656
    },
    "new_weights": {
      "GOOGL": 0.039169,
      "GOOG": 0.03363,
      "XOM": 0.053336,
      "CVX": 0.042096,
      "WMT": 0.009887,
      "MU": 0.015265,
      "CSCO": 0.016375,
      "OXY": 0.041312,
      "CMCSA": 0.061041,
      "CVS": 0.027685,
      "INTU": 0.067636
    }
  },
  {
    "date": "2023-10-31",
    "pre_value": 10658532.61,
    "post_value": 10658532.61,
    "cost": 0.0,
    "turnover": 0.561881,
    "old_weights": {
      "TSLA": 0.0,
      "AAPL": 0.0,
      "AMZN": 0.0,
      "NVDA": 0.0,
      "MSFT": 0.0,
      "AMD": 0.0,
      "META": 0.0,
      "GOOGL": 0.039169,
      "NFLX": 0.0,
      "GOOG": 0.03363,
      "BABA": 0.0,
      "XOM": 0.053336,
      "CVX": 0.042096,
      "DIS": 0.0,
      "CRM": 0.0,
      "JPM": 0.0,
      "BAC": 0.0,
      "AVGO": 0.0,
      "TSM": 0.0,
      "PYPL": 0.0,
      "INTC": 0.0,
      "PFE": 0.0,
      "QCOM": 0.0,
      "MRK": 0.0,
      "VZ": 0.0,
      "WMT": 0.009887,
      "NKE": 0.0,
      "MU": 0.015265,
      "CSCO": 0.016375,
      "C": 0.0,
      "SHOP": 0.0,
      "XYZ": 0.0,
      "OXY": 0.041312,
      "CMCSA": 0.061041,
      "WFC": 0.0,
      "PEP": 0.0,
      "SNOW": 0.0,
      "KO": 0.0,
      "COIN": 0.0,
      "T": 0.0,
      "CVS": 0.027685,
      "INTU": 0.067636,
      "LRCX": 0.0,
      "F": 0.0,
      "SBUX": 0.0,
      "BMY": 0.0,
      "NOW": 0.0,
      "MS": 0.0,
      "NIO": 0.0,
      "SCHW": 0.0
    },
    "new_weights": {
      "AMZN": 0.006756,
      "MSFT": 0.029765,
      "XOM": 0.014018,
      "INTC": 0.032924,
      "VZ": 0.038132,
      "WMT": 0.02425,
      "OXY": 0.00318,
      "T": 0.059594
    }
  },
  {
    "date": "2023-11-30",
    "pre_value": 10859195.19,
    "post_value": 10859195.19,
    "cost": 0.0,
    "turnover": 0.412112,
    "old_weights": {
      "TSLA": 0.0,
      "AAPL": 0.0,
      "AMZN": 0.006756,
      "NVDA": 0.0,
      "MSFT": 0.029765,
      "AMD": 0.0,
      "META": 0.0,
      "GOOGL": 0.0,
      "NFLX": 0.0,
      "GOOG": 0.0,
      "BABA": 0.0,
      "XOM": 0.014018,
      "CVX": 0.0,
      "DIS": 0.0,
      "CRM": 0.0,
      "JPM": 0.0,
      "BAC": 0.0,
      "AVGO": 0.0,
      "TSM": 0.0,
      "PYPL": 0.0,
      "INTC": 0.032924,
      "PFE": 0.0,
      "QCOM": 0.0,
      "MRK": 0.0,
      "VZ": 0.038132,
      "WMT": 0.02425,
      "NKE": 0.0,
      "MU": 0.0,
      "CSCO": 0.0,
      "C": 0.0,
      "SHOP": 0.0,
      "XYZ": 0.0,
      "OXY": 0.00318,
      "CMCSA": 0.0,
      "WFC": 0.0,
      "PEP": 0.0,
      "SNOW": 0.0,
      "KO": 0.0,
      "COIN": 0.0,
      "T": 0.059594,
      "CVS": 0.0,
      "INTU": 0.0,
      "LRCX": 0.0,
      "F": 0.0,
      "SBUX": 0.0,
      "BMY": 0.0,
      "NOW": 0.0,
      "MS": 0.0,
      "NIO": 0.0,
      "SCHW": 0.0
    },
    "new_weights": {
      "MSFT": 0.086051,
      "DIS": 0.006348,
      "CRM": 0.012814,
      "JPM": 0.008504,
      "INTC": 0.090727,
      "QCOM": 0.005408,
      "VZ": 0.018148,
      "MU": 0.007354,
      "C": 0.035411,
      "WFC": 0.007225,
      "SNOW": 0.003379,
      "COIN": 0.1,
      "T": 0.060565,
      "CVS": 0.012984,
      "NOW": 0.029434
    }
  },
  {
    "date": "2023-12-29",
    "pre_value": 11501781.35,
    "post_value": 11501781.35,
    "cost": 0.0,
    "turnover": 0.612747,
    "old_weights": {
      "TSLA": 0.0,
      "AAPL": 0.0,
      "AMZN": 0.0,
      "NVDA": 0.0,
      "MSFT": 0.086051,
      "AMD": 0.0,
      "META": 0.0,
      "GOOGL": 0.0,
      "NFLX": 0.0,
      "GOOG": 0.0,
      "BABA": 0.0,
      "XOM": 0.0,
      "CVX": 0.0,
      "DIS": 0.006348,
      "CRM": 0.012814,
      "JPM": 0.008504,
      "BAC": 0.0,
      "AVGO": 0.0,
      "TSM": 0.0,
      "PYPL": 0.0,
      "INTC": 0.090727,
      "PFE": 0.0,
      "QCOM": 0.005408,
      "MRK": 0.0,
      "VZ": 0.018148,
      "WMT": 0.0,
      "NKE": 0.0,
      "MU": 0.007354,
      "CSCO": 0.0,
      "C": 0.035411,
      "SHOP": 0.0,
      "XYZ": 0.0,
      "OXY": 0.0,
      "CMCSA": 0.0,
      "WFC": 0.007225,
      "PEP": 0.0,
      "SNOW": 0.003379,
      "KO": 0.0,
      "COIN": 0.1,
      "T": 0.060565,
      "CVS": 0.012984,
      "INTU": 0.0,
      "LRCX": 0.0,
      "F": 0.0,
      "SBUX": 0.0,
      "BMY": 0.0,
      "NOW": 0.029434,
      "MS": 0.0,
      "NIO": 0.0,
      "SCHW": 0.0
    },
    "new_weights": {
      "MSFT": 0.1,
      "AMD": 0.016095,
      "NFLX": 0.056508,
      "CRM": 0.054071,
      "JPM": 0.056469,
      "AVGO": 0.080669,
      "INTC": 0.1,
      "QCOM": 0.023537,
      "MRK": 0.0667,
      "VZ": 0.049361,
      "C": 0.051857,
      "XYZ": 0.081772,
      "WFC": 0.026456,
      "COIN": 0.1,
      "CVS": 0.042415,
      "NOW": 0.035897
    }
  },
  {
    "date": "2024-01-31",
    "pre_value": 11394696.07,
    "post_value": 11394696.07,
    "cost": 0.0,
    "turnover": 1.045604,
    "old_weights": {
      "TSLA": 0.0,
      "AAPL": 0.0,
      "AMZN": 0.0,
      "NVDA": 0.0,
      "MSFT": 0.1,
      "AMD": 0.016095,
      "META": 0.0,
      "GOOGL": 0.0,
      "NFLX": 0.056508,
      "GOOG": 0.0,
      "BABA": 0.0,
      "XOM": 0.0,
      "CVX": 0.0,
      "DIS": 0.0,
      "CRM": 0.054071,
      "JPM": 0.056469,
      "BAC": 0.0,
      "AVGO": 0.080669,
      "TSM": 0.0,
      "PYPL": 0.0,
      "INTC": 0.1,
      "PFE": 0.0,
      "QCOM": 0.023537,
      "MRK": 0.0667,
      "VZ": 0.049361,
      "WMT": 0.0,
      "NKE": 0.0,
      "MU": 0.0,
      "CSCO": 0.0,
      "C": 0.051857,
      "SHOP": 0.0,
      "XYZ": 0.081772,
      "OXY": 0.0,
      "CMCSA": 0.0,
      "WFC": 0.026456,
      "PEP": 0.0,
      "SNOW": 0.0,
      "KO": 0.0,
      "COIN": 0.1,
      "T": 0.0,
      "CVS": 0.042415,
      "INTU": 0.0,
      "LRCX": 0.0,
      "F": 0.0,
      "SBUX": 0.0,
      "BMY": 0.0,
      "NOW": 0.035897,
      "MS": 0.0,
      "NIO": 0.0,
      "SCHW": 0.0
    },
    "new_weights": {
      "NVDA": 0.030316,
      "AMD": 0.09569,
      "AVGO": 0.016542,
      "NFLX": 0.092296,
      "UBER": 0.1,
      "COIN": 0.019183,
      "SMCI": 0.041727,
      "JPM": 0.081277,
      "CRM": 0.069961,
      "MARA": 0.023461,
      "QCOM": 0.007339,
      "C": 0.1,
      "MRK": 0.1,
      "NOW": 0.070576,
      "VZ": 0.1,
      "XYZ": 0.010336,
      "AFRM": 0.033551,
      "CVS": 0.007745
    }
  },
  {
    "date": "2024-02-29",
    "pre_value": 12705274.54,
    "post_value": 12705274.54,
    "cost": 0.0,
    "turnover": 0.795685,
    "old_weights": {
      "TSLA": 0.0,
      "NVDA": 0.030316,
      "AAPL": 0.0,
      "AMD": 0.09569,
      "MSFT": 0.0,
      "AMZN": 0.0,
      "META": 0.0,
      "GOOGL": 0.0,
      "AVGO": 0.016542,
      "GOOG": 0.0,
      "NFLX": 0.092296,
      "XOM": 0.0,
      "INTC": 0.0,
      "UBER": 0.1,
      "COIN": 0.019183,
      "SMCI": 0.041727,
      "BABA": 0.0,
      "CVX": 0.0,
      "JPM": 0.081277,
      "CRM": 0.069961,
      "BAC": 0.0,
      "MARA": 0.023461,
      "PFE": 0.0,
      "WMT": 0.0,
      "QCOM": 0.007339,
      "DIS": 0.0,
      "MU": 0.0,
      "TSM": 0.0,
      "PYPL": 0.0,
      "PLTR": 0.0,
      "ORCL": 0.0,
      "CSCO": 0.0,
      "NKE": 0.0,
      "SNOW": 0.0,
      "C": 0.1,
      "MRK": 0.1,
      "PEP": 0.0,
      "SBUX": 0.0,
      "KO": 0.0,
      "NOW": 0.070576,
      "VZ": 0.1,
      "WFC": 0.0,
      "CMCSA": 0.0,
      "SHOP": 0.0,
      "INTU": 0.0,
      "BMY": 0.0,
      "LRCX": 0.0,
      "XYZ": 0.010336,
      "AFRM": 0.033551,
      "CVS": 0.007745
    },
    "new_weights": {
      "NVDA": 0.064807,
      "AMD": 0.024909,
      "META": 0.048279,
      "AVGO": 0.040652,
      "NFLX": 0.030929,
      "UBER": 0.040191,
      "SMCI": 0.023247,
      "JPM": 0.096602,
      "CRM": 0.076913,
      "MARA": 0.028587,
      "WMT": 0.056283,
      "QCOM": 0.04216,
      "DIS": 0.043742,
      "TSM": 0.024178,
      "C": 0.085909,
      "MRK": 0.1,
      "VZ": 0.060331,
      "WFC": 0.059601,
      "CVS": 0.05268
    }
  },
  {
    "date": "2024-03-28",
    "pre_value": 13358463.88,
    "post_value": 13358463.88,
    "cost": 0.0,
    "turnover": 0.761588,
    "old_weights": {
      "TSLA": 0.0,
      "NVDA": 0.064807,
      "AAPL": 0.0,
      "AMD": 0.024909,
      "MSFT": 0.0,
      "AMZN": 0.0,
      "META": 0.048279,
      "GOOGL": 0.0,
      "AVGO": 0.040652,
      "GOOG": 0.0,
      "NFLX": 0.030929,
      "XOM": 0.0,
      "INTC": 0.0,
      "UBER": 0.040191,
      "COIN": 0.0,
      "SMCI": 0.023247,
      "BABA": 0.0,
      "CVX": 0.0,
      "JPM": 0.096602,
      "CRM": 0.076913,
      "BAC": 0.0,
      "MARA": 0.028587,
      "PFE": 0.0,
      "WMT": 0.056283,
      "QCOM": 0.04216,
      "DIS": 0.043742,
      "MU": 0.0,
      "TSM": 0.024178,
      "PYPL": 0.0,
      "PLTR": 0.0,
      "ORCL": 0.0,
      "CSCO": 0.0,
      "NKE": 0.0,
      "SNOW": 0.0,
      "C": 0.085909,
      "MRK": 0.1,
      "PEP": 0.0,
      "SBUX": 0.0,
      "KO": 0.0,
      "NOW": 0.0,
      "VZ": 0.060331,
      "WFC": 0.059601,
      "CMCSA": 0.0,
      "SHOP": 0.0,
      "INTU": 0.0,
      "BMY": 0.0,
      "LRCX": 0.0,
      "XYZ": 0.0,
      "AFRM": 0.0,
      "CVS": 0.05268
    },
    "new_weights": {
      "NVDA": 0.1,
      "META": 0.030821,
      "NFLX": 0.064362,
      "XOM": 0.09683,
      "COIN": 0.011038,
      "SMCI": 0.044019,
      "JPM": 0.082644,
      "WMT": 0.1,
      "DIS": 0.1,
      "MU": 0.022505,
      "TSM": 0.008609,
      "PLTR": 0.005462,
      "C": 0.087066,
      "MRK": 0.1,
      "KO": 0.009218,
      "VZ": 0.08764,
      "WFC": 0.009058,
      "BMY": 0.017902,
      "CVS": 0.022827
    }
  },
  {
    "date": "2024-04-30",
    "pre_value": 12727978.54,
    "post_value": 12727978.54,
    "cost": 0.0,
    "turnover": 0.903237,
    "old_weights": {
      "TSLA": 0.0,
      "NVDA": 0.1,
      "AAPL": 0.0,
      "AMD": 0.0,
      "MSFT": 0.0,
      "AMZN": 0.0,
      "META": 0.030821,
      "GOOGL": 0.0,
      "AVGO": 0.0,
      "GOOG": 0.0,
      "NFLX": 0.064362,
      "XOM": 0.09683,
      "INTC": 0.0,
      "UBER": 0.0,
      "COIN": 0.011038,
      "SMCI": 0.044019,
      "BABA": 0.0,
      "CVX": 0.0,
      "JPM": 0.082644,
      "CRM": 0.0,
      "BAC": 0.0,
      "MARA": 0.0,
      "PFE": 0.0,
      "WMT": 0.1,
      "QCOM": 0.0,
      "DIS": 0.1,
      "MU": 0.022505,
      "TSM": 0.008609,
      "PYPL": 0.0,
      "PLTR": 0.005462,
      "ORCL": 0.0,
      "CSCO": 0.0,
      "NKE": 0.0,
      "SNOW": 0.0,
      "C": 0.087066,
      "MRK": 0.1,
      "PEP": 0.0,
      "SBUX": 0.0,
      "KO": 0.009218,
      "NOW": 0.0,
      "VZ": 0.08764,
      "WFC": 0.009058,
      "CMCSA": 0.0,
      "SHOP": 0.0,
      "INTU": 0.0,
      "BMY": 0.017902,
      "LRCX": 0.0,
      "XYZ": 0.0,
      "AFRM": 0.0,
      "CVS": 0.022827
    },
    "new_weights": {
      "NVDA": 0.049805,
      "GOOGL": 0.003588,
      "GOOG": 0.010809,
      "XOM": 0.1,
      "COIN": 0.027746,
      "SMCI": 0.013196,
      "CVX": 0.043308,
      "JPM": 0.010838,
      "WMT": 0.070403,
      "QCOM": 0.006858,
      "DIS": 0.060234,
      "MU": 0.050994,
      "PYPL": 0.012184,
      "PLTR": 0.017897,
      "MRK": 0.042057,
      "PEP": 0.040723,
      "KO": 0.043883,
      "WFC": 0.1
    }
  },
  {
    "date": "2024-05-31",
    "pre_value": 13097925.77,
    "post_value": 13097925.77,
    "cost": 0.0,
    "turnover": 0.644647,
    "old_weights": {
      "TSLA": 0.0,
      "NVDA": 0.049805,
      "AAPL": 0.0,
      "AMD": 0.0,
      "MSFT": 0.0,
      "AMZN": 0.0,
      "META": 0.0,
      "GOOGL": 0.003588,
      "AVGO": 0.0,
      "GOOG": 0.010809,
      "NFLX": 0.0,
      "XOM": 0.1,
      "INTC": 0.0,
      "UBER": 0.0,
      "COIN": 0.027746,
      "SMCI": 0.013196,
      "BABA": 0.0,
      "CVX": 0.043308,
      "JPM": 0.010838,
      "CRM": 0.0,
      "BAC": 0.0,
      "MARA": 0.0,
      "PFE": 0.0,
      "WMT": 0.070403,
      "QCOM": 0.006858,
      "DIS": 0.060234,
      "MU": 0.050994,
      "TSM": 0.0,
      "PYPL": 0.012184,
      "PLTR": 0.017897,
      "ORCL": 0.0,
      "CSCO": 0.0,
      "NKE": 0.0,
      "SNOW": 0.0,
      "C": 0.0,
      "MRK": 0.042057,
      "PEP": 0.040723,
      "SBUX": 0.0,
      "KO": 0.043883,
      "NOW": 0.0,
      "VZ": 0.0,
      "WFC": 0.1,
      "CMCSA": 0.0,
      "SHOP": 0.0,
      "INTU": 0.0,
      "BMY": 0.0,
      "LRCX": 0.0,
      "XYZ": 0.0,
      "AFRM": 0.0,
      "CVS": 0.0
    },
    "new_weights": {
      "NVDA": 0.084904,
      "AAPL": 0.019151,
      "GOOGL": 0.06843,
      "GOOG": 0.076964,
      "XOM": 0.1,
      "CVX": 0.026734,
      "JPM": 0.014946,
      "BAC": 0.078508,
      "PFE": 0.059242,
      "WMT": 0.1,
      "QCOM": 0.038379,
      "MU": 0.052265,
      "C": 0.004282,
      "PEP": 0.038166,
      "KO": 0.050589,
      "VZ": 0.031066,
      "WFC": 0.079345
    }
  },
  {
    "date": "2024-06-28",
    "pre_value": 13386386.28,
    "post_value": 13386386.28,
    "cost": 0.0,
    "turnover": 0.593653,
    "old_weights": {
      "TSLA": 0.0,
      "NVDA": 0.084904,
      "AAPL": 0.019151,
      "AMD": 0.0,
      "MSFT": 0.0,
      "AMZN": 0.0,
      "META": 0.0,
      "GOOGL": 0.06843,
      "AVGO": 0.0,
      "GOOG": 0.076964,
      "NFLX": 0.0,
      "XOM": 0.1,
      "INTC": 0.0,
      "UBER": 0.0,
      "COIN": 0.0,
      "SMCI": 0.0,
      "BABA": 0.0,
      "CVX": 0.026734,
      "JPM": 0.014946,
      "CRM": 0.0,
      "BAC": 0.078508,
      "MARA": 0.0,
      "PFE": 0.059242,
      "WMT": 0.1,
      "QCOM": 0.038379,
      "DIS": 0.0,
      "MU": 0.052265,
      "TSM": 0.0,
      "PYPL": 0.0,
      "PLTR": 0.0,
      "ORCL": 0.0,
      "CSCO": 0.0,
      "NKE": 0.0,
      "SNOW": 0.0,
      "C": 0.004282,
      "MRK": 0.0,
      "PEP": 0.038166,
      "SBUX": 0.0,
      "KO": 0.050589,
      "NOW": 0.0,
      "VZ": 0.031066,
      "WFC": 0.079345,
      "CMCSA": 0.0,
      "SHOP": 0.0,
      "INTU": 0.0,
      "BMY": 0.0,
      "LRCX": 0.0,
      "XYZ": 0.0,
      "AFRM": 0.0,
      "CVS": 0.0
    },
    "new_weights": {
      "TSLA": 0.018416,
      "NVDA": 0.074304,
      "AAPL": 0.1,
      "GOOGL": 0.065916,
      "GOOG": 0.068049,
      "XOM": 0.024765,
      "BAC": 0.024807,
      "PFE": 0.027047,
      "WMT": 0.1,
      "TSM": 0.090185,
      "KO": 0.061489,
      "VZ": 0.019807,
      "WFC": 0.055231
    }
  },
  {
    "date": "2024-07-31",
    "pre_value": 13443302.75,
    "post_value": 13443302.75,
    "cost": 0.0,
    "turnover": 0.887153,
    "old_weights": {
      "TSLA": 0.018416,
      "NVDA": 0.074304,
      "AAPL": 0.1,
      "AMD": 0.0,
      "MSFT": 0.0,
      "AMZN": 0.0,
      "META": 0.0,
      "GOOGL": 0.065916,
      "AVGO": 0.0,
      "GOOG": 0.068049,
      "NFLX": 0.0,
      "XOM": 0.024765,
      "INTC": 0.0,
      "UBER": 0.0,
      "COIN": 0.0,
      "SMCI": 0.0,
      "BABA": 0.0,
      "CVX": 0.0,
      "JPM": 0.0,
      "CRM": 0.0,
      "BAC": 0.024807,
      "MARA": 0.0,
      "PFE": 0.027047,
      "WMT": 0.1,
      "QCOM": 0.0,
      "DIS": 0.0,
      "MU": 0.0,
      "TSM": 0.090185,
      "PYPL": 0.0,
      "PLTR": 0.0,
      "ORCL": 0.0,
      "CSCO": 0.0,
      "NKE": 0.0,
      "SNOW": 0.0,
      "C": 0.0,
      "MRK": 0.0,
      "PEP": 0.0,
      "SBUX": 0.0,
      "KO": 0.061489,
      "NOW": 0.0,
      "VZ": 0.019807,
      "WFC": 0.055231,
      "CMCSA": 0.0,
      "SHOP": 0.0,
      "INTU": 0.0,
      "BMY": 0.0,
      "LRCX": 0.0,
      "XYZ": 0.0,
      "AFRM": 0.0,
      "CVS": 0.0
    },
    "new_weights": {
      "TSLA": 0.026256,
      "NVDA": 0.09186,
      "AAPL": 0.1,
      "AVGO": 0.008892,
      "NFLX": 0.057962,
      "JPM": 0.084401,
      "BAC": 0.020369,
      "PFE": 0.1,
      "WMT": 0.1,
      "PLTR": 0.008356,
      "ORCL": 0.080062,
      "CSCO": 0.015777,
      "KO": 0.092874,
      "NOW": 0.030795,
      "VZ": 0.039957,
      "CMCSA": 0.070727,
      "BMY": 0.071713
    }
  },
  {
    "date": "2024-08-30",
    "pre_value": 13960320.57,
    "post_value": 13960320.57,
    "cost": 0.0,
    "turnover": 0.745463,
    "old_weights": {
      "TSLA": 0.026256,
      "NVDA": 0.09186,
      "AAPL": 0.1,
      "AMD": 0.0,
      "MSFT": 0.0,
      "AMZN": 0.0,
      "META": 0.0,
      "GOOGL": 0.0,
      "AVGO": 0.008892,
      "GOOG": 0.0,
      "NFLX": 0.057962,
      "XOM": 0.0,
      "INTC": 0.0,
      "UBER": 0.0,
      "COIN": 0.0,
      "SMCI": 0.0,
      "BABA": 0.0,
      "CVX": 0.0,
      "JPM": 0.084401,
      "CRM": 0.0,
      "BAC": 0.020369,
      "MARA": 0.0,
      "PFE": 0.1,
      "WMT": 0.1,
      "QCOM": 0.0,
      "DIS": 0.0,
      "MU": 0.0,
      "TSM": 0.0,
      "PYPL": 0.0,
      "PLTR": 0.008356,
      "ORCL": 0.080062,
      "CSCO": 0.015777,
      "NKE": 0.0,
      "SNOW": 0.0,
      "C": 0.0,
      "MRK": 0.0,
      "PEP": 0.0,
      "SBUX": 0.0,
      "KO": 0.092874,
      "NOW": 0.030795,
      "VZ": 0.039957,
      "WFC": 0.0,
      "CMCSA": 0.070727,
      "SHOP": 0.0,
      "INTU": 0.0,
      "BMY": 0.071713,
      "LRCX": 0.0,
      "XYZ": 0.0,
      "AFRM": 0.0,
      "CVS": 0.0
    },
    "new_weights": {
      "AAPL": 0.072695,
      "AVGO": 0.011454,
      "BABA": 0.019462,
      "JPM": 0.051666,
      "WMT": 0.1,
      "PYPL": 0.02595,
      "PLTR": 0.06741,
      "ORCL": 0.052228,
      "SBUX": 0.016371,
      "KO": 0.1,
      "NOW": 0.090537,
      "VZ": 0.013184,
      "SHOP": 0.015553,
      "BMY": 0.1,
      "AFRM": 0.013758
    }
  },
  {
    "date": "2024-09-30",
    "pre_value": 14569821.3,
    "post_value": 14569821.3,
    "cost": 0.0,
    "turnover": 0.505609,
    "old_weights": {
      "TSLA": 0.0,
      "NVDA": 0.0,
      "AAPL": 0.072695,
      "AMD": 0.0,
      "MSFT": 0.0,
      "AMZN": 0.0,
      "META": 0.0,
      "GOOGL": 0.0,
      "AVGO": 0.011454,
      "GOOG": 0.0,
      "NFLX": 0.0,
      "XOM": 0.0,
      "INTC": 0.0,
      "UBER": 0.0,
      "COIN": 0.0,
      "SMCI": 0.0,
      "BABA": 0.019462,
      "CVX": 0.0,
      "JPM": 0.051666,
      "CRM": 0.0,
      "BAC": 0.0,
      "MARA": 0.0,
      "PFE": 0.0,
      "WMT": 0.1,
      "QCOM": 0.0,
      "DIS": 0.0,
      "MU": 0.0,
      "TSM": 0.0,
      "PYPL": 0.02595,
      "PLTR": 0.06741,
      "ORCL": 0.052228,
      "CSCO": 0.0,
      "NKE": 0.0,
      "SNOW": 0.0,
      "C": 0.0,
      "MRK": 0.0,
      "PEP": 0.0,
      "SBUX": 0.016371,
      "KO": 0.1,
      "NOW": 0.090537,
      "VZ": 0.013184,
      "WFC": 0.0,
      "CMCSA": 0.0,
      "SHOP": 0.015553,
      "INTU": 0.0,
      "BMY": 0.1,
      "LRCX": 0.0,
      "XYZ": 0.0,
      "AFRM": 0.013758,
      "CVS": 0.0
    },
    "new_weights": {
      "XOM": 0.001671,
      "BABA": 0.1,
      "WMT": 0.1,
      "PYPL": 0.1,
      "PLTR": 0.081322,
      "ORCL": 0.04454,
      "NKE": 0.001626,
      "PEP": 0.051418,
      "SBUX": 0.035595,
      "KO": 0.1,
      "NOW": 0.001228,
      "VZ": 0.027592,
      "BMY": 0.1,
      "AFRM": 0.013361
    }
  },
  {
    "date": "2024-10-31",
    "pre_value": 14627902.9,
    "post_value": 14627902.9,
    "cost": 0.0,
    "turnover": 0.563156,
    "old_weights": {
      "TSLA": 0.0,
      "NVDA": 0.0,
      "AAPL": 0.0,
      "AMD": 0.0,
      "MSFT": 0.0,
      "AMZN": 0.0,
      "META": 0.0,
      "GOOGL": 0.0,
      "AVGO": 0.0,
      "GOOG": 0.0,
      "NFLX": 0.0,
      "XOM": 0.001671,
      "INTC": 0.0,
      "UBER": 0.0,
      "COIN": 0.0,
      "SMCI": 0.0,
      "BABA": 0.1,
      "CVX": 0.0,
      "JPM": 0.0,
      "CRM": 0.0,
      "BAC": 0.0,
      "MARA": 0.0,
      "PFE": 0.0,
      "WMT": 0.1,
      "QCOM": 0.0,
      "DIS": 0.0,
      "MU": 0.0,
      "TSM": 0.0,
      "PYPL": 0.1,
      "PLTR": 0.081322,
      "ORCL": 0.04454,
      "CSCO": 0.0,
      "NKE": 0.001626,
      "SNOW": 0.0,
      "C": 0.0,
      "MRK": 0.0,
      "PEP": 0.051418,
      "SBUX": 0.035595,
      "KO": 0.1,
      "NOW": 0.001228,
      "VZ": 0.027592,
      "WFC": 0.0,
      "CMCSA": 0.0,
      "SHOP": 0.0,
      "INTU": 0.0,
      "BMY": 0.1,
      "LRCX": 0.0,
      "XYZ": 0.0,
      "AFRM": 0.013361,
      "CVS": 0.0
    },
    "new_weights": {
      "NFLX": 0.025895,
      "BABA": 0.070577,
      "CRM": 0.027748,
      "WMT": 0.1,
      "TSM": 0.013447,
      "PYPL": 0.030547,
      "PLTR": 0.1,
      "ORCL": 0.070938,
      "SBUX": 0.035289,
      "WFC": 0.069326,
      "CMCSA": 0.029224,
      "SHOP": 0.041424,
      "BMY": 0.091554,
      "AFRM": 0.033212
    }
  },
  {
    "date": "2024-11-29",
    "pre_value": 16610883.56,
    "post_value": 16610883.56,
    "cost": 0.0,
    "turnover": 0.61017,
    "old_weights": {
      "TSLA": 0.0,
      "NVDA": 0.0,
      "AAPL": 0.0,
      "AMD": 0.0,
      "MSFT": 0.0,
      "AMZN": 0.0,
      "META": 0.0,
      "GOOGL": 0.0,
      "AVGO": 0.0,
      "GOOG": 0.0,
      "NFLX": 0.025895,
      "XOM": 0.0,
      "INTC": 0.0,
      "UBER": 0.0,
      "COIN": 0.0,
      "SMCI": 0.0,
      "BABA": 0.070577,
      "CVX": 0.0,
      "JPM": 0.0,
      "CRM": 0.027748,
      "BAC": 0.0,
      "MARA": 0.0,
      "PFE": 0.0,
      "WMT": 0.1,
      "QCOM": 0.0,
      "DIS": 0.0,
      "MU": 0.0,
      "TSM": 0.013447,
      "PYPL": 0.030547,
      "PLTR": 0.1,
      "ORCL": 0.070938,
      "CSCO": 0.0,
      "NKE": 0.0,
      "SNOW": 0.0,
      "C": 0.0,
      "MRK": 0.0,
      "PEP": 0.0,
      "SBUX": 0.035289,
      "KO": 0.0,
      "NOW": 0.0,
      "VZ": 0.0,
      "WFC": 0.069326,
      "CMCSA": 0.029224,
      "SHOP": 0.041424,
      "INTU": 0.0,
      "BMY": 0.091554,
      "LRCX": 0.0,
      "XYZ": 0.0,
      "AFRM": 0.033212,
      "CVS": 0.0
    },
    "new_weights": {
      "TSLA": 0.027152,
      "NFLX": 0.049048,
      "BABA": 0.045743,
      "CVX": 0.059418,
      "CRM": 0.056338,
      "WMT": 0.1,
      "DIS": 0.1,
      "TSM": 0.00115,
      "PLTR": 0.1,
      "ORCL": 0.079081,
      "CSCO": 0.052907,
      "SNOW": 0.043921,
      "SBUX": 0.024471,
      "VZ": 0.044594,
      "WFC": 0.026217,
      "CMCSA": 0.009365,
      "SHOP": 0.080594,
      "BMY": 0.1
    }
  },
  {
    "date": "2024-12-31",
    "pre_value": 16118598.42,
    "post_value": 16118598.42,
    "cost": 0.0,
    "turnover": 0.704535,
    "old_weights": {
      "TSLA": 0.027152,
      "NVDA": 0.0,
      "AAPL": 0.0,
      "AMD": 0.0,
      "MSFT": 0.0,
      "AMZN": 0.0,
      "META": 0.0,
      "GOOGL": 0.0,
      "AVGO": 0.0,
      "GOOG": 0.0,
      "NFLX": 0.049048,
      "XOM": 0.0,
      "INTC": 0.0,
      "UBER": 0.0,
      "COIN": 0.0,
      "SMCI": 0.0,
      "BABA": 0.045743,
      "CVX": 0.059418,
      "JPM": 0.0,
      "CRM": 0.056338,
      "BAC": 0.0,
      "MARA": 0.0,
      "PFE": 0.0,
      "WMT": 0.1,
      "QCOM": 0.0,
      "DIS": 0.1,
      "MU": 0.0,
      "TSM": 0.00115,
      "PYPL": 0.0,
      "PLTR": 0.1,
      "ORCL": 0.079081,
      "CSCO": 0.052907,
      "NKE": 0.0,
      "SNOW": 0.043921,
      "C": 0.0,
      "MRK": 0.0,
      "PEP": 0.0,
      "SBUX": 0.024471,
      "KO": 0.0,
      "NOW": 0.0,
      "VZ": 0.044594,
      "WFC": 0.026217,
      "CMCSA": 0.009365,
      "SHOP": 0.080594,
      "INTU": 0.0,
      "BMY": 0.1,
      "LRCX": 0.0,
      "XYZ": 0.0,
      "AFRM": 0.0,
      "CVS": 0.0
    },
    "new_weights": {
      "TSLA": 0.017389,
      "AAPL": 0.042563,
      "GOOGL": 0.035149,
      "AVGO": 0.019902,
      "GOOG": 0.026991,
      "NFLX": 0.058611,
      "CRM": 0.015911,
      "WMT": 0.037248,
      "DIS": 0.1,
      "TSM": 0.058227,
      "PLTR": 0.1,
      "CSCO": 0.037548,
      "SNOW": 0.037265,
      "NOW": 0.002838,
      "WFC": 0.040972,
      "SHOP": 0.026387,
      "BMY": 0.056135
    }
  },
  {
    "date": "2025-01-31",
    "pre_value": 16861973.91,
    "post_value": 16861973.91,
    "cost": 0.0,
    "turnover": 0.694705,
    "old_weights": {
      "TSLA": 0.017389,
      "NVDA": 0.0,
      "AAPL": 0.042563,
      "AMD": 0.0,
      "MSFT": 0.0,
      "AMZN": 0.0,
      "META": 0.0,
      "GOOGL": 0.035149,
      "AVGO": 0.019902,
      "GOOG": 0.026991,
      "NFLX": 0.058611,
      "XOM": 0.0,
      "INTC": 0.0,
      "UBER": 0.0,
      "COIN": 0.0,
      "SMCI": 0.0,
      "BABA": 0.0,
      "CVX": 0.0,
      "JPM": 0.0,
      "CRM": 0.015911,
      "BAC": 0.0,
      "MARA": 0.0,
      "PFE": 0.0,
      "WMT": 0.037248,
      "QCOM": 0.0,
      "DIS": 0.1,
      "MU": 0.0,
      "TSM": 0.058227,
      "PYPL": 0.0,
      "PLTR": 0.1,
      "ORCL": 0.0,
      "CSCO": 0.037548,
      "NKE": 0.0,
      "SNOW": 0.037265,
      "C": 0.0,
      "MRK": 0.0,
      "PEP": 0.0,
      "SBUX": 0.0,
      "KO": 0.0,
      "NOW": 0.002838,
      "VZ": 0.0,
      "WFC": 0.040972,
      "CMCSA": 0.0,
      "SHOP": 0.026387,
      "INTU": 0.0,
      "BMY": 0.056135,
      "LRCX": 0.0,
      "XYZ": 0.0,
      "AFRM": 0.0,
      "CVS": 0.0
    },
    "new_weights": {
      "TSLA": 0.019644,
      "AMZN": 0.021366,
      "PLTR": 0.052805,
      "GOOGL": 0.017395,
      "GOOG": 0.012263,
      "NFLX": 0.1,
      "WMT": 0.1,
      "MRVL": 0.013063,
      "RGTI": 0.034705,
      "CVX": 0.055562,
      "MRK": 0.000131,
      "SNOW": 0.051315,
      "KO": 0.025846,
      "C": 0.026626,
      "DIS": 0.1,
      "HOOD": 0.016801
    }
  },
  {
    "date": "2025-02-28",
    "pre_value": 16561066.29,
    "post_value": 16561066.29,
    "cost": 0.0,
    "turnover": 0.795655,
    "old_weights": {
      "TSLA": 0.019644,
      "NVDA": 0.0,
      "AAPL": 0.0,
      "MSTR": 0.0,
      "MSFT": 0.0,
      "META": 0.0,
      "AMZN": 0.021366,
      "AVGO": 0.0,
      "PLTR": 0.052805,
      "GOOGL": 0.017395,
      "AMD": 0.0,
      "COIN": 0.0,
      "GOOG": 0.012263,
      "NFLX": 0.1,
      "TSM": 0.0,
      "SMCI": 0.0,
      "JPM": 0.0,
      "MU": 0.0,
      "CRM": 0.0,
      "ORCL": 0.0,
      "XOM": 0.0,
      "UBER": 0.0,
      "INTC": 0.0,
      "BAC": 0.0,
      "WMT": 0.1,
      "MRVL": 0.013063,
      "BABA": 0.0,
      "NOW": 0.0,
      "RGTI": 0.034705,
      "QCOM": 0.0,
      "CVX": 0.055562,
      "MARA": 0.0,
      "WFC": 0.0,
      "MRK": 0.000131,
      "CSCO": 0.0,
      "PFE": 0.0,
      "SNOW": 0.051315,
      "INTU": 0.0,
      "KO": 0.025846,
      "IONQ": 0.0,
      "C": 0.026626,
      "SOUN": 0.0,
      "DELL": 0.0,
      "DIS": 0.1,
      "PEP": 0.0,
      "APO": 0.0,
      "HOOD": 0.016801,
      "NKE": 0.0,
      "LRCX": 0.0,
      "WDAY": 0.0
    },
    "new_weights": {
      "META": 0.065738,
      "AVGO": 0.006677,
      "PLTR": 0.006194,
      "NFLX": 0.026424,
      "JPM": 0.010525,
      "WMT": 0.074836,
      "BABA": 0.1,
      "RGTI": 0.025778,
      "CVX": 0.009175,
      "MRK": 0.003713,
      "CSCO": 0.058503,
      "PFE": 0.001219,
      "KO": 0.1,
      "C": 0.041731,
      "SOUN": 0.001577,
      "HOOD": 0.001458,
      "NKE": 0.00752
    }
  },
  {
    "date": "2025-03-31",
    "pre_value": 16132928.84,
    "post_value": 16132928.84,
    "cost": 0.0,
    "turnover": 0.550785,
    "old_weights": {
      "TSLA": 0.0,
      "NVDA": 0.0,
      "AAPL": 0.0,
      "MSTR": 0.0,
      "MSFT": 0.0,
      "META": 0.065738,
      "AMZN": 0.0,
      "AVGO": 0.006677,
      "PLTR": 0.006194,
      "GOOGL": 0.0,
      "AMD": 0.0,
      "COIN": 0.0,
      "GOOG": 0.0,
      "NFLX": 0.026424,
      "TSM": 0.0,
      "SMCI": 0.0,
      "JPM": 0.010525,
      "MU": 0.0,
      "CRM": 0.0,
      "ORCL": 0.0,
      "XOM": 0.0,
      "UBER": 0.0,
      "INTC": 0.0,
      "BAC": 0.0,
      "WMT": 0.074836,
      "MRVL": 0.0,
      "BABA": 0.1,
      "NOW": 0.0,
      "RGTI": 0.025778,
      "QCOM": 0.0,
      "CVX": 0.009175,
      "MARA": 0.0,
      "WFC": 0.0,
      "MRK": 0.003713,
      "CSCO": 0.058503,
      "PFE": 0.001219,
      "SNOW": 0.0,
      "INTU": 0.0,
      "KO": 0.1,
      "IONQ": 0.0,
      "C": 0.041731,
      "SOUN": 0.001577,
      "DELL": 0.0,
      "DIS": 0.0,
      "PEP": 0.0,
      "APO": 0.0,
      "HOOD": 0.001458,
      "NKE": 0.00752,
      "LRCX": 0.0,
      "WDAY": 0.0
    },
    "new_weights": {
      "XOM": 0.079798,
      "UBER": 0.052264,
      "INTC": 0.003436,
      "BABA": 0.1,
      "CVX": 0.1,
      "CSCO": 0.007431,
      "KO": 0.1
    }
  },
  {
    "date": "2025-04-30",
    "pre_value": 15661108.79,
    "post_value": 15661108.79,
    "cost": 0.0,
    "turnover": 0.361362,
    "old_weights": {
      "TSLA": 0.0,
      "NVDA": 0.0,
      "AAPL": 0.0,
      "MSTR": 0.0,
      "MSFT": 0.0,
      "META": 0.0,
      "AMZN": 0.0,
      "AVGO": 0.0,
      "PLTR": 0.0,
      "GOOGL": 0.0,
      "AMD": 0.0,
      "COIN": 0.0,
      "GOOG": 0.0,
      "NFLX": 0.0,
      "TSM": 0.0,
      "SMCI": 0.0,
      "JPM": 0.0,
      "MU": 0.0,
      "CRM": 0.0,
      "ORCL": 0.0,
      "XOM": 0.079798,
      "UBER": 0.052264,
      "INTC": 0.003436,
      "BAC": 0.0,
      "WMT": 0.0,
      "MRVL": 0.0,
      "BABA": 0.1,
      "NOW": 0.0,
      "RGTI": 0.0,
      "QCOM": 0.0,
      "CVX": 0.1,
      "MARA": 0.0,
      "WFC": 0.0,
      "MRK": 0.0,
      "CSCO": 0.007431,
      "PFE": 0.0,
      "SNOW": 0.0,
      "INTU": 0.0,
      "KO": 0.1,
      "IONQ": 0.0,
      "C": 0.0,
      "SOUN": 0.0,
      "DELL": 0.0,
      "DIS": 0.0,
      "PEP": 0.0,
      "APO": 0.0,
      "HOOD": 0.0,
      "NKE": 0.0,
      "LRCX": 0.0,
      "WDAY": 0.0
    },
    "new_weights": {
      "PLTR": 0.041684,
      "NFLX": 0.006784,
      "UBER": 0.012077,
      "BABA": 0.017957,
      "KO": 0.1
    }
  },
  {
    "date": "2025-05-30",
    "pre_value": 15762062.82,
    "post_value": 15762062.82,
    "cost": 0.0,
    "turnover": 0.191905,
    "old_weights": {
      "TSLA": 0.0,
      "NVDA": 0.0,
      "AAPL": 0.0,
      "MSTR": 0.0,
      "MSFT": 0.0,
      "META": 0.0,
      "AMZN": 0.0,
      "AVGO": 0.0,
      "PLTR": 0.041684,
      "GOOGL": 0.0,
      "AMD": 0.0,
      "COIN": 0.0,
      "GOOG": 0.0,
      "NFLX": 0.006784,
      "TSM": 0.0,
      "SMCI": 0.0,
      "JPM": 0.0,
      "MU": 0.0,
      "CRM": 0.0,
      "ORCL": 0.0,
      "XOM": 0.0,
      "UBER": 0.012077,
      "INTC": 0.0,
      "BAC": 0.0,
      "WMT": 0.0,
      "MRVL": 0.0,
      "BABA": 0.017957,
      "NOW": 0.0,
      "RGTI": 0.0,
      "QCOM": 0.0,
      "CVX": 0.0,
      "MARA": 0.0,
      "WFC": 0.0,
      "MRK": 0.0,
      "CSCO": 0.0,
      "PFE": 0.0,
      "SNOW": 0.0,
      "INTU": 0.0,
      "KO": 0.1,
      "IONQ": 0.0,
      "C": 0.0,
      "SOUN": 0.0,
      "DELL": 0.0,
      "DIS": 0.0,
      "PEP": 0.0,
      "APO": 0.0,
      "HOOD": 0.0,
      "NKE": 0.0,
      "LRCX": 0.0,
      "WDAY": 0.0
    },
    "new_weights": {
      "MSTR": 0.015209,
      "PLTR": 0.033087,
      "NFLX": 0.020065,
      "RGTI": 0.000469,
      "INTU": 0.028664,
      "KO": 0.019013,
      "IONQ": 0.014664
    }
  },
  {
    "date": "2025-06-30",
    "pre_value": 15900005.62,
    "post_value": 15900005.62,
    "cost": 0.0,
    "turnover": 0.328086,
    "old_weights": {
      "TSLA": 0.0,
      "NVDA": 0.0,
      "AAPL": 0.0,
      "MSTR": 0.015209,
      "MSFT": 0.0,
      "META": 0.0,
      "AMZN": 0.0,
      "AVGO": 0.0,
      "PLTR": 0.033087,
      "GOOGL": 0.0,
      "AMD": 0.0,
      "COIN": 0.0,
      "GOOG": 0.0,
      "NFLX": 0.020065,
      "TSM": 0.0,
      "SMCI": 0.0,
      "JPM": 0.0,
      "MU": 0.0,
      "CRM": 0.0,
      "ORCL": 0.0,
      "XOM": 0.0,
      "UBER": 0.0,
      "INTC": 0.0,
      "BAC": 0.0,
      "WMT": 0.0,
      "MRVL": 0.0,
      "BABA": 0.0,
      "NOW": 0.0,
      "RGTI": 0.000469,
      "QCOM": 0.0,
      "CVX": 0.0,
      "MARA": 0.0,
      "WFC": 0.0,
      "MRK": 0.0,
      "CSCO": 0.0,
      "PFE": 0.0,
      "SNOW": 0.0,
      "INTU": 0.028664,
      "KO": 0.019013,
      "IONQ": 0.014664,
      "C": 0.0,
      "SOUN": 0.0,
      "DELL": 0.0,
      "DIS": 0.0,
      "PEP": 0.0,
      "APO": 0.0,
      "HOOD": 0.0,
      "NKE": 0.0,
      "LRCX": 0.0,
      "WDAY": 0.0
    },
    "new_weights": {
      "MSFT": 0.022219,
      "COIN": 0.033915,
      "NFLX": 0.1,
      "ORCL": 0.047222,
      "INTU": 0.019174,
      "IONQ": 0.002115,
      "HOOD": 0.054979
    }
  },
  {
    "date": "2025-07-31",
    "pre_value": 15971823.38,
    "post_value": 15971823.38,
    "cost": 0.0,
    "turnover": 0.992436,
    "old_weights": {
      "TSLA": 0.0,
      "NVDA": 0.0,
      "AAPL": 0.0,
      "MSTR": 0.0,
      "MSFT": 0.022219,
      "META": 0.0,
      "AMZN": 0.0,
      "AVGO": 0.0,
      "PLTR": 0.0,
      "GOOGL": 0.0,
      "AMD": 0.0,
      "COIN": 0.033915,
      "GOOG": 0.0,
      "NFLX": 0.1,
      "TSM": 0.0,
      "SMCI": 0.0,
      "JPM": 0.0,
      "MU": 0.0,
      "CRM": 0.0,
      "ORCL": 0.047222,
      "XOM": 0.0,
      "UBER": 0.0,
      "INTC": 0.0,
      "BAC": 0.0,
      "WMT": 0.0,
      "MRVL": 0.0,
      "BABA": 0.0,
      "NOW": 0.0,
      "RGTI": 0.0,
      "QCOM": 0.0,
      "CVX": 0.0,
      "MARA": 0.0,
      "WFC": 0.0,
      "MRK": 0.0,
      "CSCO": 0.0,
      "PFE": 0.0,
      "SNOW": 0.0,
      "INTU": 0.019174,
      "KO": 0.0,
      "IONQ": 0.002115,
      "C": 0.0,
      "SOUN": 0.0,
      "DELL": 0.0,
      "DIS": 0.0,
      "PEP": 0.0,
      "APO": 0.0,
      "HOOD": 0.054979,
      "NKE": 0.0,
      "LRCX": 0.0,
      "WDAY": 0.0
    },
    "new_weights": {
      "NVDA": 0.1,
      "MSFT": 0.1,
      "META": 0.044632,
      "AVGO": 0.040518,
      "GOOGL": 0.041847,
      "AMD": 0.1,
      "GOOG": 0.030898,
      "ORCL": 0.1,
      "XOM": 0.019478,
      "CVX": 0.037819,
      "CSCO": 0.012731,
      "SNOW": 0.075689,
      "INTU": 0.1,
      "C": 0.044289,
      "DELL": 0.019489,
      "DIS": 0.032021,
      "HOOD": 0.1,
      "NKE": 0.000588
    }
  },
  {
    "date": "2025-08-29",
    "pre_value": 15602119.0,
    "post_value": 15602119.0,
    "cost": 0.0,
    "turnover": 1.021498,
    "old_weights": {
      "TSLA": 0.0,
      "NVDA": 0.1,
      "AAPL": 0.0,
      "MSTR": 0.0,
      "MSFT": 0.1,
      "META": 0.044632,
      "AMZN": 0.0,
      "AVGO": 0.040518,
      "PLTR": 0.0,
      "GOOGL": 0.041847,
      "AMD": 0.1,
      "COIN": 0.0,
      "GOOG": 0.030898,
      "NFLX": 0.0,
      "TSM": 0.0,
      "SMCI": 0.0,
      "JPM": 0.0,
      "MU": 0.0,
      "CRM": 0.0,
      "ORCL": 0.1,
      "XOM": 0.019478,
      "UBER": 0.0,
      "INTC": 0.0,
      "BAC": 0.0,
      "WMT": 0.0,
      "MRVL": 0.0,
      "BABA": 0.0,
      "NOW": 0.0,
      "RGTI": 0.0,
      "QCOM": 0.0,
      "CVX": 0.037819,
      "MARA": 0.0,
      "WFC": 0.0,
      "MRK": 0.0,
      "CSCO": 0.012731,
      "PFE": 0.0,
      "SNOW": 0.075689,
      "INTU": 0.1,
      "KO": 0.0,
      "IONQ": 0.0,
      "C": 0.044289,
      "SOUN": 0.0,
      "DELL": 0.019489,
      "DIS": 0.032021,
      "PEP": 0.0,
      "APO": 0.0,
      "HOOD": 0.1,
      "NKE": 0.000588,
      "LRCX": 0.0,
      "WDAY": 0.0
    },
    "new_weights": {
      "NVDA": 0.027126,
      "AAPL": 0.012416,
      "MSFT": 0.015918,
      "META": 0.006073,
      "AVGO": 0.005311,
      "GOOGL": 0.06834,
      "AMD": 0.066383,
      "GOOG": 0.061359,
      "ORCL": 0.09213,
      "XOM": 0.093718,
      "UBER": 0.018269,
      "INTC": 0.03152,
      "BAC": 0.024885,
      "BABA": 0.060009,
      "CVX": 0.1,
      "MRK": 0.014679,
      "PFE": 0.016515,
      "SNOW": 0.019034,
      "C": 0.081609,
      "PEP": 0.027656,
      "HOOD": 0.082357,
      "NKE": 0.06363,
      "LRCX": 0.011064
    }
  },
  {
    "date": "2025-09-30",
    "pre_value": 17251747.28,
    "post_value": 17251747.28,
    "cost": 0.0,
    "turnover": 1.060481,
    "old_weights": {
      "TSLA": 0.0,
      "NVDA": 0.027126,
      "AAPL": 0.012416,
      "MSTR": 0.0,
      "MSFT": 0.015918,
      "META": 0.006073,
      "AMZN": 0.0,
      "AVGO": 0.005311,
      "PLTR": 0.0,
      "GOOGL": 0.06834,
      "AMD": 0.066383,
      "COIN": 0.0,
      "GOOG": 0.061359,
      "NFLX": 0.0,
      "TSM": 0.0,
      "SMCI": 0.0,
      "JPM": 0.0,
      "MU": 0.0,
      "CRM": 0.0,
      "ORCL": 0.09213,
      "XOM": 0.093718,
      "UBER": 0.018269,
      "INTC": 0.03152,
      "BAC": 0.024885,
      "WMT": 0.0,
      "MRVL": 0.0,
      "BABA": 0.060009,
      "NOW": 0.0,
      "RGTI": 0.0,
      "QCOM": 0.0,
      "CVX": 0.1,
      "MARA": 0.0,
      "WFC": 0.0,
      "MRK": 0.014679,
      "CSCO": 0.0,
      "PFE": 0.016515,
      "SNOW": 0.019034,
      "INTU": 0.0,
      "KO": 0.0,
      "IONQ": 0.0,
      "C": 0.081609,
      "SOUN": 0.0,
      "DELL": 0.0,
      "DIS": 0.0,
      "PEP": 0.027656,
      "APO": 0.0,
      "HOOD": 0.082357,
      "NKE": 0.06363,
      "LRCX": 0.011064,
      "WDAY": 0.0
    },
    "new_weights": {
      "TSLA": 0.048514,
      "NVDA": 0.002953,
      "AAPL": 0.054259,
      "AVGO": 0.035821,
      "PLTR": 0.039142,
      "GOOGL": 0.1,
      "GOOG": 0.1,
      "MU": 0.008994,
      "ORCL": 0.029073,
      "XOM": 0.04531,
      "INTC": 0.077078,
      "WMT": 0.053626,
      "BABA": 0.1,
      "RGTI": 0.071278,
      "CVX": 0.051928,
      "MRK": 0.003307,
      "PFE": 0.027492,
      "PEP": 0.006629,
      "HOOD": 0.064026,
      "LRCX": 0.080571
    }
  },
  {
    "date": "2025-10-31",
    "pre_value": 19138689.5,
    "post_value": 19138689.5,
    "cost": 0.0,
    "turnover": 0.835184,
    "old_weights": {
      "TSLA": 0.048514,
      "NVDA": 0.002953,
      "AAPL": 0.054259,
      "MSTR": 0.0,
      "MSFT": 0.0,
      "META": 0.0,
      "AMZN": 0.0,
      "AVGO": 0.035821,
      "PLTR": 0.039142,
      "GOOGL": 0.1,
      "AMD": 0.0,
      "COIN": 0.0,
      "GOOG": 0.1,
      "NFLX": 0.0,
      "TSM": 0.0,
      "SMCI": 0.0,
      "JPM": 0.0,
      "MU": 0.008994,
      "CRM": 0.0,
      "ORCL": 0.029073,
      "XOM": 0.04531,
      "UBER": 0.0,
      "INTC": 0.077078,
      "BAC": 0.0,
      "WMT": 0.053626,
      "MRVL": 0.0,
      "BABA": 0.1,
      "NOW": 0.0,
      "RGTI": 0.071278,
      "QCOM": 0.0,
      "CVX": 0.051928,
      "MARA": 0.0,
      "WFC": 0.0,
      "MRK": 0.003307,
      "CSCO": 0.0,
      "PFE": 0.027492,
      "SNOW": 0.0,
      "INTU": 0.0,
      "KO": 0.0,
      "IONQ": 0.0,
      "C": 0.0,
      "SOUN": 0.0,
      "DELL": 0.0,
      "DIS": 0.0,
      "PEP": 0.006629,
      "APO": 0.0,
      "HOOD": 0.064026,
      "NKE": 0.0,
      "LRCX": 0.080571,
      "WDAY": 0.0
    },
    "new_weights": {
      "TSLA": 0.044342,
      "AAPL": 0.095681,
      "GOOGL": 0.1,
      "AMD": 0.02311,
      "GOOG": 0.1,
      "MU": 0.1,
      "ORCL": 0.007973,
      "XOM": 0.038594,
      "INTC": 0.1,
      "BAC": 0.001456,
      "WMT": 0.007006,
      "BABA": 0.044446,
      "RGTI": 0.058688,
      "CVX": 0.005585,
      "MRK": 0.011703,
      "SNOW": 0.016212,
      "KO": 0.091526,
      "PEP": 0.1,
      "HOOD": 0.025506,
      "WDAY": 0.028171
    }
  },
  {
    "date": "2025-11-28",
    "pre_value": 19166898.0,
    "post_value": 19166898.0,
    "cost": 0.0,
    "turnover": 0.626778,
    "old_weights": {
      "TSLA": 0.044342,
      "NVDA": 0.0,
      "AAPL": 0.095681,
      "MSTR": 0.0,
      "MSFT": 0.0,
      "META": 0.0,
      "AMZN": 0.0,
      "AVGO": 0.0,
      "PLTR": 0.0,
      "GOOGL": 0.1,
      "AMD": 0.02311,
      "COIN": 0.0,
      "GOOG": 0.1,
      "NFLX": 0.0,
      "TSM": 0.0,
      "SMCI": 0.0,
      "JPM": 0.0,
      "MU": 0.1,
      "CRM": 0.0,
      "ORCL": 0.007973,
      "XOM": 0.038594,
      "UBER": 0.0,
      "INTC": 0.1,
      "BAC": 0.001456,
      "WMT": 0.007006,
      "MRVL": 0.0,
      "BABA": 0.044446,
      "NOW": 0.0,
      "RGTI": 0.058688,
      "QCOM": 0.0,
      "CVX": 0.005585,
      "MARA": 0.0,
      "WFC": 0.0,
      "MRK": 0.011703,
      "CSCO": 0.0,
      "PFE": 0.0,
      "SNOW": 0.016212,
      "INTU": 0.0,
      "KO": 0.091526,
      "IONQ": 0.0,
      "C": 0.0,
      "SOUN": 0.0,
      "DELL": 0.0,
      "DIS": 0.0,
      "PEP": 0.1,
      "APO": 0.0,
      "HOOD": 0.025506,
      "NKE": 0.0,
      "LRCX": 0.0,
      "WDAY": 0.028171
    },
    "new_weights": {
      "AAPL": 0.091571,
      "AVGO": 0.008426,
      "GOOGL": 0.1,
      "AMD": 0.001384,
      "GOOG": 0.1,
      "MU": 0.1,
      "XOM": 0.059291,
      "INTC": 0.064508,
      "WMT": 0.1,
      "MRVL": 0.03514,
      "RGTI": 0.001036,
      "MRK": 0.1,
      "CSCO": 0.050914,
      "KO": 0.1,
      "PEP": 0.070833
    }
  },
  {
    "date": "2025-12-31",
    "pre_value": 19268369.45,
    "post_value": 19268369.45,
    "cost": 0.0,
    "turnover": 0.473732,
    "old_weights": {
      "TSLA": 0.0,
      "NVDA": 0.0,
      "AAPL": 0.091571,
      "MSTR": 0.0,
      "MSFT": 0.0,
      "META": 0.0,
      "AMZN": 0.0,
      "AVGO": 0.008426,
      "PLTR": 0.0,
      "GOOGL": 0.1,
      "AMD": 0.001384,
      "COIN": 0.0,
      "GOOG": 0.1,
      "NFLX": 0.0,
      "TSM": 0.0,
      "SMCI": 0.0,
      "JPM": 0.0,
      "MU": 0.1,
      "CRM": 0.0,
      "ORCL": 0.0,
      "XOM": 0.059291,
      "UBER": 0.0,
      "INTC": 0.064508,
      "BAC": 0.0,
      "WMT": 0.1,
      "MRVL": 0.03514,
      "BABA": 0.0,
      "NOW": 0.0,
      "RGTI": 0.001036,
      "QCOM": 0.0,
      "CVX": 0.0,
      "MARA": 0.0,
      "WFC": 0.0,
      "MRK": 0.1,
      "CSCO": 0.050914,
      "PFE": 0.0,
      "SNOW": 0.0,
      "INTU": 0.0,
      "KO": 0.1,
      "IONQ": 0.0,
      "C": 0.0,
      "SOUN": 0.0,
      "DELL": 0.0,
      "DIS": 0.0,
      "PEP": 0.070833,
      "APO": 0.0,
      "HOOD": 0.0,
      "NKE": 0.0,
      "LRCX": 0.0,
      "WDAY": 0.0
    },
    "new_weights": {
      "GOOGL": 0.069599,
      "AMD": 0.010043,
      "GOOG": 0.073474,
      "MU": 0.080961,
      "CRM": 0.04063,
      "XOM": 0.071515,
      "WMT": 0.1,
      "WFC": 0.046419,
      "MRK": 0.1,
      "CSCO": 0.05071,
      "KO": 0.084317,
      "C": 0.046341,
      "PEP": 0.044342,
      "APO": 0.000432
    }
  },
  {
    "date": "2026-01-30",
    "pre_value": 20618626.69,
    "post_value": 20618626.69,
    "cost": 0.0,
    "turnover": 0.481191,
    "old_weights": {
      "TSLA": 0.0,
      "NVDA": 0.0,
      "AAPL": 0.0,
      "MSTR": 0.0,
      "MSFT": 0.0,
      "META": 0.0,
      "AMZN": 0.0,
      "AVGO": 0.0,
      "PLTR": 0.0,
      "GOOGL": 0.069599,
      "AMD": 0.010043,
      "COIN": 0.0,
      "GOOG": 0.073474,
      "NFLX": 0.0,
      "TSM": 0.0,
      "SMCI": 0.0,
      "JPM": 0.0,
      "MU": 0.080961,
      "CRM": 0.04063,
      "ORCL": 0.0,
      "XOM": 0.071515,
      "UBER": 0.0,
      "INTC": 0.0,
      "BAC": 0.0,
      "WMT": 0.1,
      "MRVL": 0.0,
      "BABA": 0.0,
      "NOW": 0.0,
      "RGTI": 0.0,
      "QCOM": 0.0,
      "CVX": 0.0,
      "MARA": 0.0,
      "WFC": 0.046419,
      "MRK": 0.1,
      "CSCO": 0.05071,
      "PFE": 0.0,
      "SNOW": 0.0,
      "INTU": 0.0,
      "KO": 0.084317,
      "IONQ": 0.0,
      "C": 0.046341,
      "SOUN": 0.0,
      "DELL": 0.0,
      "DIS": 0.0,
      "PEP": 0.044342,
      "APO": 0.000432,
      "HOOD": 0.0,
      "NKE": 0.0,
      "LRCX": 0.0,
      "WDAY": 0.0
    },
    "new_weights": {
      "GOOGL": 0.062549,
      "MU": 0.06878,
      "GOOG": 0.068025,
      "SNDK": 0.054388,
      "WMT": 0.1,
      "LRCX": 0.003972,
      "XOM": 0.1,
      "CSCO": 0.064251,
      "CVX": 0.094238,
      "C": 0.066607,
      "MRK": 0.1,
      "KO": 0.1,
      "VZ": 0.08407
    }
  }
]